{"data":[{"_createdAt":"2024-07-24T11:21:10Z","_id":"ba146f87-7ad8-4b36-ad4e-39feebd267c8","_rev":"9tRlS5SpoWcKRb9PRCtUQF","_type":"tool","_updatedAt":"2024-07-25T15:18:52Z","affiliateLink":false,"affiliatePosition":-3037,"defunct":{"defunctReason":"No Longer Available","defunctStatus":false},"duplicate":false,"favCount":1,"id":"ba146f87-7ad8-4b36-ad4e-39feebd267c8","mainImage":{"_type":"image","asset":{"_ref":"image-766633442f5fbfb81eae714b25bb241a7e06c328-2517x1194-png","_type":"reference"}},"popularityScore":1,"pricing":["Free Trial"],"publishedAt":"2024-07-25T02:36:00.000Z","publishedAt_timestamp":1721874960000,"reviewStats":{"reviewCount":0,"reviewScore":0},"slug":{"_type":"slug","current":"mediaio"},"slugIndex":"mediaio","socialLinks":["https://www.facebook.com/MediaioOfficial","https://www.youtube.com/channel/UC5yZCPN2Xds61GKl_i90ZtQ","https://www.instagram.com/mediaioofficial/"],"sponsorOfTheDay":false,"sponsored":true,"startingPrice":"9.99/mo","status":"In Review","tagsIndex":["image-editing","video-editing","video-generators"],"thumbnail":{"_type":"image","asset":{"_ref":"image-4ef10c4169eea09b65311d130eaa82cc83fceaad-32x32-png","_type":"reference"}},"toolCategories":[{"_createdAt":"2023-01-01T18:45:30Z","_id":"UnZ2THkIAtRzfNq86WfeWy","_rev":"lEP6oyvyuxfmkHVVQb8UQy","_type":"toolCategory","_updatedAt":"2024-07-22T08:33:54Z","businessFunctionCategory":{"_ref":"dc25203a-766c-42dd-9e18-72199dbcff5f","_type":"reference"},"categoryCode":"image-3","categoryName":"image editing","mainImage":{"_type":"image","asset":{"_ref":"image-3ae9ca70e502cf3d0b22a86617063e79b8c9f729-3643x2049-jpg","_type":"reference"}},"mainImageAltText":"Discover AI Image Editors","parentCategory":{"_ref":"8MM31Kxa78RqfoWPxffkKt","_type":"reference"},"positionLockIn":[{"_key":"1defe13c13cf","_ref":"2e54f716-1070-4492-abde-68be88113565","_type":"reference"},{"_key":"64bc27c55022","_ref":"b1278b6e-eb65-41e3-b3f7-0df86c451539","_type":"reference"},{"_key":"dc4c92168284","_ref":"5cb400a6-5ca3-46d9-9ac8-dbe32cc99d5f","_type":"reference"}],"relatedCategories":[{"_key":"ogeScKmv83khEevZcZdGta","_ref":"2650f8d3-164b-4c4b-bb51-aa0f91bf8c0d","_type":"reference"},{"_key":"528CbQkA3sHikFV1sbChzV","_ref":"18c28701-ecbf-446d-a50d-29285561c411","_type":"reference"}],"seoImage":{"_type":"image","asset":{"_ref":"image-3ae9ca70e502cf3d0b22a86617063e79b8c9f729-3643x2049-jpg","_type":"reference"}},"seoTitle":"Image Editing Tools & Software Using AI in [year]","slug":{"_type":"slug","current":"image-editing"},"sponsoredTools":[{"_key":"fb838be0d517","_ref":"02a25982-fba2-49af-a8d4-0742b4dd7f4a","_type":"reference"},{"_key":"96ef9aac6d79","_ref":"76fc6bc5-6d6d-4984-bf57-3b3aa40b6c5d","_type":"reference"}],"tableOfContents":{"_type":"tableOfContents","items":[{"_key":"d043f87009c3","anchor":"#ai-image-editors","label":"AI Image Editors"},{"_key":"4515ee359ade","anchor":"#empowering-creatives-and-professionals-with-ai","label":"Empowering Creatives and Professionals with AI"},{"_key":"486b1489b0da","anchor":"#harnessing-ai-for-transformative-image-editing","label":"Harnessing AI for Transformative Image Editing"}]},"tagline":"Quickly Refine Visuals with These [count] AI Image Editors","title":"AI Image Editors - Transforming Your Visuals with Precision"},{"_createdAt":"2023-01-01T18:45:52Z","_id":"UnZ2THkIAtRzfNq86WfrII","_rev":"GmsMATw7FFr29OeLDADDBV","_type":"toolCategory","_updatedAt":"2024-07-22T08:25:17Z","businessFunctionCategory":{"_ref":"dc25203a-766c-42dd-9e18-72199dbcff5f","_type":"reference"},"categoryCode":"video-2","categoryName":"video editing","mainImage":{"_type":"image","asset":{"_ref":"image-46647727e970e8a23ff141e6c6573e38a4d4b671-2478x1394-jpg","_type":"reference"}},"mainImageAltText":"Research AI Video Editors","parentCategory":{"_ref":"45DxCNvEQNdNriBtbNYKMC","_type":"reference"},"positionLockIn":[{"_key":"fb2e72500942","_ref":"877a393f-831d-41c4-9ba5-dc2dc5b947b6","_type":"reference"},{"_key":"930d31d26a2c","_ref":"f0dd39b7-ce95-4b70-b4e3-214566ec9e42","_type":"reference"},{"_key":"abf3cc802c3f","_ref":"a2ef477a-1d6c-4fba-9e7f-2654b317e62e","_type":"reference"}],"relatedCategories":[{"_key":"7Uq6HgUsYttekH7fErzVK3","_ref":"a1ca8317-f0c1-4640-86d1-2b3872905e4d","_type":"reference"},{"_key":"14TwMfrhBc2xwAnczFdozk","_ref":"B8o7xf7Q4mKeMEiyAO326s","_type":"reference"}],"seoImage":{"_type":"image","asset":{"_ref":"image-46647727e970e8a23ff141e6c6573e38a4d4b671-2478x1394-jpg","_type":"reference"}},"seoTitle":"AI Video Editing Tools & Software in [year]","slug":{"_type":"slug","current":"video-editing"},"sponsoredTools":[{"_key":"808b407d005d","_ref":"a4d44807-583b-4e8c-849d-a21504b068b0","_type":"reference"},{"_key":"68c7430c611b","_ref":"02a25982-fba2-49af-a8d4-0742b4dd7f4a","_type":"reference"}],"tableOfContents":{"_type":"tableOfContents","items":[{"_key":"9aa3e86984da","anchor":"#ai-video-editors","label":"AI Video Editors"},{"_key":"d67a9e47da28","anchor":"#why-ai-video-editors-are-a-game-changer","label":"Why AI Video Editors Are a Game Changer"},{"_key":"11401f5ff617","anchor":"#the-ai-driven-video-landscape","label":"Looking Ahead: The AI-Driven Video Landscape"}]},"tagline":"[count] AI Video Editor Tools That Speed Up the Editing Process","title":"AI Video Editors - Your Creative Catalyst"},{"_createdAt":"2023-10-12T10:24:19Z","_id":"a1ca8317-f0c1-4640-86d1-2b3872905e4d","_rev":"QzKmTQ46u4hbvI8bkJXlEn","_type":"toolCategory","_updatedAt":"2024-07-25T15:09:34Z","businessFunctionCategory":{"_ref":"dc25203a-766c-42dd-9e18-72199dbcff5f","_type":"reference"},"categoryCode":"video-1","categoryName":"video generators","parentCategory":{"_ref":"45DxCNvEQNdNriBtbNYKMC","_type":"reference"},"positionLockIn":[{"_key":"637502f5ab62","_ref":"76291196-da25-4a45-a1f2-4095a55eb2bd","_type":"reference"},{"_key":"f2a01cc064f1","_ref":"57cc5d70-7469-431e-a467-890d6d3ffdac","_type":"reference"},{"_key":"8f65bbc10b47","_ref":"8a178d10-3c62-47c6-9cfe-7d1800fb18b5","_type":"reference"}],"relatedCategories":[{"_key":"pbVx23Uct8BFJWoTGLUb4q","_ref":"UnZ2THkIAtRzfNq86WfrII","_type":"reference"},{"_key":"b4woo4NyLzk7WLJRGAmg8H","_ref":"a1ca8317-f0c1-4640-86d1-2b3872905e4d","_type":"reference"},{"_key":"3rhwNLcWJNPdENVJS6gYgS","_ref":"49222099-e48a-4a41-8a5c-1dfcd8f1639f","_type":"reference"}],"seoImage":{"_type":"image","asset":{"_ref":"image-6c12c1929641165095558f7b8204ae259b4ea730-600x327-gif","_type":"reference"}},"seoTitle":"AI Video Generator Tools & Software in [year]","slug":{"_type":"slug","current":"video-generators"},"sponsoredTools":[{"_key":"3618b995c06a","_ref":"4d16b3c8-5c6f-4f85-b0a1-21b0e306a118","_type":"reference"},{"_key":"627f228b86fc","_ref":"ba146f87-7ad8-4b36-ad4e-39feebd267c8","_type":"reference"}],"tableOfContents":{"_type":"tableOfContents","items":[{"_key":"51dcb7fb4075","anchor":"#ai-video-generation-tools","label":"AI Video Generation Tools"},{"_key":"f7f9cdb2aded","anchor":"#the-magic-of-ai-video-generators","label":"Revolutionizing Storytelling: The Magic of AI Video Generators"},{"_key":"6c221bb9e165","anchor":"#unleashing-creativity-across-industries","label":"Unleashing Creativity Across Industries"},{"_key":"569a09fc26bc","anchor":"#embrace-the-future-of-video-with-ai","label":"Embrace the Future of Video with AI"}]},"tagline":"Craft Breathtaking Visual Stories with These [count] AI Video Generation Tools","title":"AI Video Generation Tools - Igniting Your Imagination","youtubeUrl":"https://www.youtube.com/watch?v=yRt591hlGTk"}],"toolLabel":"none","toolName":"Media.io","toolShortDescription":"Enhance, edit, and convert media effortlessly online.","toolType":[],"verified":true,"verifiedReason":"Recommended","websiteUrl":"https://www.media.io/?utm_source=other_media_sites&utm_medium=social&utm_campaign=20240724zjmmi&utm_term=futurepedia&utm_content=post_21114870_2024-07-24","youtubeUrl":"https://www.youtube.com/embed/aXZ6csJKCFg?si=R9HS9GUX7cTnUOHS"},{"_createdAt":"2023-02-13T03:43:51Z","_id":"0ff4e515-1eba-49ad-ae02-06b208924732","_rev":"AHd2ccTj9eT5ZoP6mSomm2","_type":"tool","_updatedAt":"2024-07-25T09:21:21Z","affiliateLink":false,"affiliatePosition":-3036,"defunct":{"defunctReason":"No Longer Available","defunctStatus":false},"duplicate":false,"favCount":62,"id":"0ff4e515-1eba-49ad-ae02-06b208924732","mainImage":{"_type":"image","asset":{"_ref":"image-05146db8b96af31ca9701bf245f29916044887d3-2527x1301-png","_type":"reference"}},"newFeatures":[],"popularityScore":202,"pricing":["Paid"],"publishedAt":"2023-02-13T03:45:07.116Z","publishedAt_timestamp":1676259907116,"reviewStats":{"reviewCount":7,"reviewScore":35},"slug":{"_type":"slug","current":"customgpt"},"slugIndex":"customgpt","socialLinks":["https://www.facebook.com/customgpt/","https://twitter.com/customgpt","https://www.linkedin.com/company/customgpt/","https://www.youtube.com/channel/UC8FQFRCUgdoeeAVeXZmVdcw"],"sponsored":true,"startingPrice":"99/month","status":"In Review","tagsIndex":["research-assistant","customer-support","chatbots"],"thumbnail":{"_type":"image","asset":{"_ref":"image-02772a8bf8245ff69634ed6b620e5733f237965c-128x128-png","_type":"reference"}},"thumbnailUrl":"https://www.google.com/s2/favicons?domain=https://customgpt.ai/&sz=128","toolCategories":[{"_createdAt":"2023-01-01T18:46:12Z","_id":"B8o7xf7Q4mKeMEiyAO3myQ","_rev":"TLttxgH8a5TkDO3GTNiGsx","_type":"toolCategory","_updatedAt":"2024-07-02T00:16:16Z","businessFunctionCategory":{"_ref":"bf29aee4-0862-4f8c-8ceb-e67b71c93da0","_type":"reference"},"categoryCode":"misc-2","categoryName":"research","mainImage":{"_type":"image","asset":{"_ref":"image-386346ea31d986ea9d0b81a8cb1b9a0d7a8513bf-1266x710-jpg","_type":"reference"}},"mainImageAltText":"Kevin testing AI research tools","parentCategory":{"_ref":"1vD6eDtgeKSQKjJSiByJSn","_type":"reference"},"positionLockIn":[{"_key":"d1a0eaa64a6f","_ref":"c7557112-5f7b-4685-a30b-6e7c4bfa1473","_type":"reference"},{"_key":"20e6ac23d4c8","_ref":"887f666c-b3af-4c7f-b16e-7e656eb3b4a6","_type":"reference"},{"_key":"c3f8139de27a","_ref":"a5e3b0a3-8e44-4d9c-b243-a04f02e12b2b","_type":"reference"}],"relatedCategories":[{"_key":"1aa139c23906","_ref":"51dceb59-b72a-4dfe-a800-dce57c5c024b","_type":"reference"},{"_key":"dcFios7G8cgH6F3hvHR2us","_ref":"kxHCIyVPfR3nkfRNFsIq36","_type":"reference"}],"seoImage":{"_type":"image","asset":{"_ref":"image-386346ea31d986ea9d0b81a8cb1b9a0d7a8513bf-1266x710-jpg","_type":"reference"}},"seoTitle":"Research Tools & Software Using AI in [year]","slug":{"_type":"slug","current":"research-assistant"},"sponsoredTools":[{"_key":"e0496de3b20d","_ref":"94df7685-6bdc-432a-abc3-3207c12b4f39","_type":"reference"},{"_key":"5002596aa3ee","_ref":"4a17873c-1521-4965-abca-f1f475df46e8","_type":"reference"}],"tableOfContents":{"_type":"tableOfContents","items":[{"_key":"2eab8dd0f5ae","anchor":"#ai-research-tools","label":"AI Research Tools"},{"_key":"dacf332f468c","anchor":"#fueling-innovation-across-every-field","label":"Fueling Innovation Across Every Field"},{"_key":"7f993f23cb67","anchor":"#worldwide-collaboration-and-ingenuity","label":"Worldwide Collaboration and Ingenuity"}]},"tagline":"Rapidly Build & Analyze Data Using These [count] AI Research Tools","title":"AI Research Tools - Your Intelligent Partner in Discovery"},{"_createdAt":"2023-01-01T18:45:58Z","_id":"UnZ2THkIAtRzfNq86WfuL0","_rev":"ZyKI2xkKo7EMNMrzTo5qoq","_type":"toolCategory","_updatedAt":"2024-07-22T08:44:34Z","businessFunctionCategory":{"_ref":"92d3a9d0-023a-47b9-b863-9b7e9055f5e0","_type":"reference"},"categoryCode":"biz-2","categoryName":"customer support","parentCategory":{"_ref":"6f0cc24a-55e6-47a4-8f49-269200573b6b","_type":"reference"},"positionLockIn":[{"_key":"f2caf93bba50","_ref":"a2c8c1ab-1440-4c36-9a68-c463e3716dc0","_type":"reference"},{"_key":"08fd8e88638c","_ref":"d30083b1-4fcb-4491-9356-3c8abdb652b6","_type":"reference"},{"_key":"df83a70e59d8","_ref":"cc19e4ef-a103-4d0d-938a-53a257f8406f","_type":"reference"}],"relatedCategories":[{"_key":"vX315MGJMk13itwd2pwDcN","_ref":"UnZ2THkIAtRzfNq86WfzKU","_type":"reference"},{"_key":"819721f813f9","_ref":"kxHCIyVPfR3nkfRNFsIGZ6","_type":"reference"}],"seoImage":{"_type":"image","asset":{"_ref":"image-714ad99e0d8ee284488b28f97689c64c5d8d26d5-1024x1024-webp","_type":"reference"}},"seoTitle":"AI for Customer Support Tools & Software in [year]","slug":{"_type":"slug","current":"customer-support"},"sponsoredTools":[{"_key":"46e362f4d07a","_ref":"94fe0ab6-0d7d-42ba-813c-11ba13479ed4","_type":"reference"},{"_key":"93b7963a69af","_ref":"7e782f82-41f2-4b93-9370-c39f5ae8e7cd","_type":"reference"}]},{"_createdAt":"2023-10-09T18:59:35Z","_id":"e9eaed2c-bcdc-4ac4-a519-5490c8e31117","_rev":"uorVjtmjRg9cfQyWdb18dn","_type":"toolCategory","_updatedAt":"2024-07-02T01:37:35Z","businessFunctionCategory":{"_ref":"92d3a9d0-023a-47b9-b863-9b7e9055f5e0","_type":"reference"},"categoryCode":"chatbot-1","categoryName":"ai chatbots","mainImage":{"_type":"image","asset":{"_ref":"image-24524b531e3afdf9efd43650c6a634ce66596ab4-3901x2195-jpg","_type":"reference"}},"mainImageAltText":"Try These AI Chatbots","parentCategory":{"_ref":"iexqLQ1Ay2ySzDYapFDJwW","_type":"reference"},"positionLockIn":[{"_key":"ceec900053d9","_ref":"e58eeb8b-739d-492c-aa67-80e934e7d732","_type":"reference"},{"_key":"f648bba85f96","_ref":"377ca812-57fd-43a7-82a4-6c2becb28552","_type":"reference"},{"_key":"8b73cf5a506a","_ref":"d1081d5c-f6e7-4b38-b67c-bbca1f1b5d87","_type":"reference"}],"relatedCategories":[{"_key":"fb8833414081","_ref":"UnZ2THkIAtRzfNq86WfuL0","_type":"reference"},{"_key":"7f718f1f8a59","_ref":"UnZ2THkIAtRzfNq86WfjaE","_type":"reference"}],"seoImage":{"_type":"image","asset":{"_ref":"image-24524b531e3afdf9efd43650c6a634ce66596ab4-3901x2195-jpg","_type":"reference"}},"seoTitle":"AI Powered Chatbots of [year]","slug":{"_type":"slug","current":"chatbots"},"sponsoredTools":[{"_key":"e8265fec11fb","_ref":"0ff4e515-1eba-49ad-ae02-06b208924732","_type":"reference"},{"_key":"81203cec132e","_ref":"4a17873c-1521-4965-abca-f1f475df46e8","_type":"reference"}],"tableOfContents":{"_type":"tableOfContents","items":[{"_key":"e5b47341ac03","anchor":"#ai-chatbot-tools","label":"AI Chatbot Tools"},{"_key":"918340d5c1c7","anchor":"#enhancing-engagement-across-industries","label":"Enhancing Engagement Across Industries"},{"_key":"d8ca4322ddfa","anchor":"#the-technical-core-of-ai-chatbots","label":"The Technical Core of AI Chatbots"},{"_key":"35ae32220f76","anchor":"#embracing-the-future-with-ai-chatbots","label":"Embracing the Future with AI Chatbots"}]},"tagline":"Revolutionize Your Communication with These [count] AI Chatbot Tools","title":"AI Chatbot Tools: Elevating Conversations with Intelligent Interactions"}],"toolName":"CustomGPT.ai","toolShortDescription":"Turn Data into Dialogue with AI-Driven Precision.","toolType":["gpt"],"verified":true,"verifiedReason":"Recommended","websiteUrl":"https://customgpt.ai?fpr=futurepedia-42"},{"_createdAt":"2024-03-20T00:35:47Z","_id":"b9a4efa0-4e9c-4689-83d6-69ee8d9314ed","_rev":"0XM93eGzBTmQdWeWVVCMXd","_type":"tool","_updatedAt":"2024-07-25T16:38:41Z","affiliateLink":false,"affiliatePosition":-3035,"defunct":{"defunctReason":"No Longer Available","defunctStatus":false},"duplicate":false,"favCount":19,"id":"b9a4efa0-4e9c-4689-83d6-69ee8d9314ed","mainImage":{"_type":"image","asset":{"_ref":"image-3d82954a70985b2fb9fad8617af03c9ac506bfb6-2521x1234-png","_type":"reference"}},"popularityScore":19,"pricing":["Freemium"],"publishedAt":"2024-03-19T00:35:00.000Z","publishedAt_timestamp":1710808500000,"reviewStats":{"reviewCount":0,"reviewScore":0},"slug":{"_type":"slug","current":"salescred-pro"},"slugIndex":"salescred-pro","socialLinks":["https://www.facebook.com/salesfuel/","https://twitter.com/salesfuel","https://www.linkedin.com/company/sales-fuel","https://www.instagram.com/salesfuel/"],"sponsored":true,"startingPrice":"39/mo","status":"In Review","tagsIndex":["customer-support","sales-assistant"],"thumbnail":{"_type":"image","asset":{"_ref":"image-a743736a9ef546c30355b8d70efffd4765156eff-128x128-png","_type":"reference"}},"toolCategories":[{"_createdAt":"2023-01-01T18:45:58Z","_id":"UnZ2THkIAtRzfNq86WfuL0","_rev":"ZyKI2xkKo7EMNMrzTo5qoq","_type":"toolCategory","_updatedAt":"2024-07-22T08:44:34Z","businessFunctionCategory":{"_ref":"92d3a9d0-023a-47b9-b863-9b7e9055f5e0","_type":"reference"},"categoryCode":"biz-2","categoryName":"customer support","parentCategory":{"_ref":"6f0cc24a-55e6-47a4-8f49-269200573b6b","_type":"reference"},"positionLockIn":[{"_key":"f2caf93bba50","_ref":"a2c8c1ab-1440-4c36-9a68-c463e3716dc0","_type":"reference"},{"_key":"08fd8e88638c","_ref":"d30083b1-4fcb-4491-9356-3c8abdb652b6","_type":"reference"},{"_key":"df83a70e59d8","_ref":"cc19e4ef-a103-4d0d-938a-53a257f8406f","_type":"reference"}],"relatedCategories":[{"_key":"vX315MGJMk13itwd2pwDcN","_ref":"UnZ2THkIAtRzfNq86WfzKU","_type":"reference"},{"_key":"819721f813f9","_ref":"kxHCIyVPfR3nkfRNFsIGZ6","_type":"reference"}],"seoImage":{"_type":"image","asset":{"_ref":"image-714ad99e0d8ee284488b28f97689c64c5d8d26d5-1024x1024-webp","_type":"reference"}},"seoTitle":"AI for Customer Support Tools & Software in [year]","slug":{"_type":"slug","current":"customer-support"},"sponsoredTools":[{"_key":"46e362f4d07a","_ref":"94fe0ab6-0d7d-42ba-813c-11ba13479ed4","_type":"reference"},{"_key":"93b7963a69af","_ref":"7e782f82-41f2-4b93-9370-c39f5ae8e7cd","_type":"reference"}]},{"_createdAt":"2023-01-01T18:46:07Z","_id":"UnZ2THkIAtRzfNq86WfzKU","_rev":"0k15mPeIL6qxT66ZGpDLEX","_type":"toolCategory","_updatedAt":"2024-07-02T01:31:47Z","businessFunctionCategory":{"_ref":"e9e5001e-0256-4761-b0f9-6196e003e40f","_type":"reference"},"categoryCode":"biz-8","categoryName":"sales","mainImage":{"_type":"image","asset":{"_ref":"image-15d50f50dbaaaddbf7f2a21f7782d3e97c153259-3901x2195-jpg","_type":"reference"}},"mainImageAltText":"Boost Sales with AI Assistance","parentCategory":{"_ref":"6f0cc24a-55e6-47a4-8f49-269200573b6b","_type":"reference"},"positionLockIn":[{"_key":"49d904b7f57d","_ref":"7dd6b75f-b257-4f78-8a26-1fc822a433c2","_type":"reference"},{"_key":"9a434da3c157","_ref":"50df6c9a-80b4-4182-83b8-7110946475ac","_type":"reference"},{"_key":"8b5c3707b2af","_ref":"fad4383f-1e7b-4f8b-be50-1a7c41529d00","_type":"reference"}],"relatedCategories":[{"_key":"mb89hfp3S5P9KPWcRUAmmT","_ref":"UnZ2THkIAtRzfNq86WfuL0","_type":"reference"}],"seoImage":{"_type":"image","asset":{"_ref":"image-15d50f50dbaaaddbf7f2a21f7782d3e97c153259-3901x2195-jpg","_type":"reference"}},"seoTitle":"AI Sales Tools & Software of [year]","slug":{"_type":"slug","current":"sales-assistant"},"sponsoredTools":[{"_key":"ce24a83b3e36","_ref":"4a17873c-1521-4965-abca-f1f475df46e8","_type":"reference"},{"_key":"921f4b743f36","_ref":"b9a4efa0-4e9c-4689-83d6-69ee8d9314ed","_type":"reference"}],"tableOfContents":{"_type":"tableOfContents","items":[{"_key":"94648a4206e5","anchor":"#ai-sales-tools","label":"AI Sales Tools"},{"_key":"f49713945e34","anchor":"#ethical-considerations-in-ai-sales-practices","label":"Ethical Considerations in AI Sales Practices"},{"_key":"cd72633dcf6c","anchor":"#revolutionizing-sales-training-with-ai","label":"Revolutionizing Sales Training with AI"},{"_key":"97d36a21a961","anchor":"#the-future-of-sales-in-the-ai-era","label":"The Future of Sales in the AI Era"}]},"tagline":"Skyrocket Sales with These [count] AI Tools","title":"AI Sales Tools: Empowering Sales Teams with Precision and Insight"}],"toolName":"SalesCred PRO","toolShortDescription":"Boost sales credibility and client trust with AI-driven insights and training.","verified":true,"verifiedReason":"Recommended","websiteUrl":"https://salesfuel.com/salescred/?utm_source=futurepedia&utm_medium=marketplace&utm_campaign=futurepedia","youtubeUrl":"https://www.youtube.com/embed/f1C7jkTBsSQ?si=bZ-KJQ2JWEtbREWn"},{"_createdAt":"2024-02-22T21:36:09Z","_id":"d1d4692e-1bcc-41e8-880c-fa5c7fad4d48","_rev":"lkqcUabRbzMsIuFy3YYTba","_type":"tool","_updatedAt":"2024-07-25T16:49:49Z","affiliateLink":false,"affiliatePosition":-3034,"defunct":{"defunctReason":"No Longer Available","defunctStatus":false},"duplicate":false,"favCount":16,"id":"d1d4692e-1bcc-41e8-880c-fa5c7fad4d48","mainImage":{"_type":"image","asset":{"_ref":"image-8daa16140f9ab3be529a461da824064a66d9fede-2522x1231-png","_type":"reference"}},"popularityScore":16,"pricing":["Paid"],"publishedAt":"2024-02-22T00:10:00.000Z","publishedAt_timestamp":1708560600000,"reviewStats":{"reviewCount":0,"reviewScore":0},"slug":{"_type":"slug","current":"ai-detector-writehuman"},"slugIndex":"ai-detector-writehuman","socialLinks":["https://www.instagram.com/writehumanai/","https://twitter.com/WriteHumanAI","https://www.facebook.com/profile.php?id=100095218522632"],"sponsored":true,"startingPrice":"12/mo","status":"In Review","tagsIndex":["education","ai-detection"],"thumbnail":{"_type":"image","asset":{"_ref":"image-8e5009f0a6edb060770b3134d8134369660ef2e5-128x128-png","_type":"reference"}},"thumbnailUrl":"https://www.google.com/s2/favicons?domain=https://writehuman.ai/ai-detector&sz=128","toolCategories":[{"_createdAt":"2023-10-12T11:06:54Z","_id":"51dceb59-b72a-4dfe-a800-dce57c5c024b","_rev":"ZyKI2xkKo7EMNMrzTo37YS","_type":"toolCategory","_updatedAt":"2024-07-21T23:53:12Z","categoryCode":"biz-1","categoryName":"education","mainImage":{"_type":"image","asset":{"_ref":"image-ebf8969e512bbd52520a9c4d3e067a8dd0004151-3901x2195-jpg","_type":"reference"}},"mainImageAltText":"Education AI Tools","parentCategory":{"_ref":"6f0cc24a-55e6-47a4-8f49-269200573b6b","_type":"reference"},"positionLockIn":[{"_key":"bed6a3f8915f","_ref":"5fd1c244-2504-4151-ad91-573e605bf1e7","_type":"reference"},{"_key":"652c56fd4616","_ref":"9b31ed37-7b51-4688-b66d-8037cfbc696d","_type":"reference"},{"_key":"01f98d1a5ef8","_ref":"b31d3fe2-fb63-46f6-9be8-7effe8acc421","_type":"reference"}],"seoImage":{"_type":"image","asset":{"_ref":"image-ebf8969e512bbd52520a9c4d3e067a8dd0004151-3901x2195-jpg","_type":"reference"}},"seoTitle":"AI Education Assistant Tools & Software of [year]","slug":{"_type":"slug","current":"education"},"sponsoredTools":[{"_key":"2bf06cf08771","_ref":"d1d4692e-1bcc-41e8-880c-fa5c7fad4d48","_type":"reference"},{"_key":"a4cf447e1065","_ref":"a79b62af-2af8-4452-98a4-649f9403abc3","_type":"reference"}],"tableOfContents":{"_type":"tableOfContents","items":[{"_key":"8ee54273a42f","anchor":"#ai-education-tools","label":"AI Education Tools"},{"_key":"6d232381c12f","anchor":"#revolutionizing-education-with-ai","label":"Revolutionizing Education with AI"},{"_key":"a227c0972d67","anchor":"#ai-driven-educational-environments","label":"AI-Driven Educational Environments"},{"_key":"5157ddb9182d","anchor":"#future-ready-education","label":"\"Future-Ready\" Education"}]},"tagline":"[count] AI Education Tools to Reshape How We Teach & Learn","title":"AI Education Tools: Empowering Educators with Tailored Solutions"},{"_createdAt":"2023-10-09T19:01:42Z","_id":"fdfe526d-9683-492e-8ad1-36eddc8eaabb","_rev":"87Q3EQD3HNMbuYcB0DdUws","_type":"toolCategory","_updatedAt":"2024-07-01T23:50:05Z","businessFunctionCategory":{"_ref":"bf29aee4-0862-4f8c-8ceb-e67b71c93da0","_type":"reference"},"categoryCode":"detect-1","categoryName":"ai detection","parentCategory":{"_ref":"iexqLQ1Ay2ySzDYapFDJwW","_type":"reference"},"positionLockIn":[{"_key":"c79a865f5386","_ref":"c6bc9109-beb0-48f9-9918-c31fc79117b1","_type":"reference"},{"_key":"57333856ced9","_ref":"3679f546-12c9-4cf6-8ce7-0007959afd84","_type":"reference"},{"_key":"d88ae66776f6","_ref":"f3fc00ca-e6fb-4e97-9e0e-ffd150a4ce37","_type":"reference"}],"relatedCategories":[{"_key":"722d86c25e68","_ref":"3d3b8adf-2e0e-43eb-b41a-1e246aef944c","_type":"reference"},{"_key":"0d4555ad960a","_ref":"B8o7xf7Q4mKeMEiyAO3myQ","_type":"reference"}],"seoImage":{"_type":"image","asset":{"_ref":"image-0f8ac3d9eac48aebc7ea4206883ac8c1f724f49e-1024x1024-webp","_type":"reference"}},"seoTitle":"AI Detection Tools & Software of [year]","slug":{"_type":"slug","current":"ai-detection"},"sponsoredTools":[{"_key":"b11ec0d36fd8","_ref":"d1d4692e-1bcc-41e8-880c-fa5c7fad4d48","_type":"reference"}]}],"toolName":"AI Detector","toolShortDescription":"Unmask AI writing with swift, user-friendly text authenticity analysis. Made by WriteHuman.","verified":true,"verifiedReason":"Recommended","websiteUrl":"https://writehuman.ai/ai-detector?utm_source=futurepedia&utm_medium=marketplace&utm_campaign=futurepedia"},{"_createdAt":"2024-03-11T00:23:54Z","_id":"4a17873c-1521-4965-abca-f1f475df46e8","_rev":"5c9rgrF529R6xkerVWUouf","_type":"tool","_updatedAt":"2024-07-24T19:17:17Z","affiliateLink":false,"affiliatePosition":-3033,"defunct":{"defunctReason":"No Longer Available","defunctStatus":false},"duplicate":false,"favCount":82,"id":"4a17873c-1521-4965-abca-f1f475df46e8","mainImage":{"_type":"image","asset":{"_ref":"image-812371fae22228b61d24398902e6f7b51cc5c7f7-2487x1223-png","_type":"reference"}},"popularityScore":182,"pricing":["Freemium"],"publishedAt":"2024-07-22T00:23:00.000Z","publishedAt_timestamp":1721607780000,"reviewStats":{"reviewCount":5,"reviewScore":25},"slug":{"_type":"slug","current":"workhack"},"slugIndex":"workhack","socialLinks":["https://www.linkedin.com/company/workhackai/","https://twitter.com/workhackai","https://www.youtube.com/@MetaformsAI"],"sponsored":true,"startingPrice":"89/mo","status":"In Review","tagsIndex":["research-assistant","sales-assistant","chatbots"],"thumbnail":{"_type":"image","asset":{"_ref":"image-4be79303d8eedf4acf4aed56111d4d0a8d63c86e-59x59-png","_type":"reference"}},"thumbnailUrl":"https://www.google.com/s2/favicons?domain=https://metaforms.ai/?via=futurepedia&sz=128","toolCategories":[{"_createdAt":"2023-01-01T18:46:12Z","_id":"B8o7xf7Q4mKeMEiyAO3myQ","_rev":"TLttxgH8a5TkDO3GTNiGsx","_type":"toolCategory","_updatedAt":"2024-07-02T00:16:16Z","businessFunctionCategory":{"_ref":"bf29aee4-0862-4f8c-8ceb-e67b71c93da0","_type":"reference"},"categoryCode":"misc-2","categoryName":"research","mainImage":{"_type":"image","asset":{"_ref":"image-386346ea31d986ea9d0b81a8cb1b9a0d7a8513bf-1266x710-jpg","_type":"reference"}},"mainImageAltText":"Kevin testing AI research tools","parentCategory":{"_ref":"1vD6eDtgeKSQKjJSiByJSn","_type":"reference"},"positionLockIn":[{"_key":"d1a0eaa64a6f","_ref":"c7557112-5f7b-4685-a30b-6e7c4bfa1473","_type":"reference"},{"_key":"20e6ac23d4c8","_ref":"887f666c-b3af-4c7f-b16e-7e656eb3b4a6","_type":"reference"},{"_key":"c3f8139de27a","_ref":"a5e3b0a3-8e44-4d9c-b243-a04f02e12b2b","_type":"reference"}],"relatedCategories":[{"_key":"1aa139c23906","_ref":"51dceb59-b72a-4dfe-a800-dce57c5c024b","_type":"reference"},{"_key":"dcFios7G8cgH6F3hvHR2us","_ref":"kxHCIyVPfR3nkfRNFsIq36","_type":"reference"}],"seoImage":{"_type":"image","asset":{"_ref":"image-386346ea31d986ea9d0b81a8cb1b9a0d7a8513bf-1266x710-jpg","_type":"reference"}},"seoTitle":"Research Tools & Software Using AI in [year]","slug":{"_type":"slug","current":"research-assistant"},"sponsoredTools":[{"_key":"e0496de3b20d","_ref":"94df7685-6bdc-432a-abc3-3207c12b4f39","_type":"reference"},{"_key":"5002596aa3ee","_ref":"4a17873c-1521-4965-abca-f1f475df46e8","_type":"reference"}],"tableOfContents":{"_type":"tableOfContents","items":[{"_key":"2eab8dd0f5ae","anchor":"#ai-research-tools","label":"AI Research Tools"},{"_key":"dacf332f468c","anchor":"#fueling-innovation-across-every-field","label":"Fueling Innovation Across Every Field"},{"_key":"7f993f23cb67","anchor":"#worldwide-collaboration-and-ingenuity","label":"Worldwide Collaboration and Ingenuity"}]},"tagline":"Rapidly Build & Analyze Data Using These [count] AI Research Tools","title":"AI Research Tools - Your Intelligent Partner in Discovery"},{"_createdAt":"2023-01-01T18:46:07Z","_id":"UnZ2THkIAtRzfNq86WfzKU","_rev":"0k15mPeIL6qxT66ZGpDLEX","_type":"toolCategory","_updatedAt":"2024-07-02T01:31:47Z","businessFunctionCategory":{"_ref":"e9e5001e-0256-4761-b0f9-6196e003e40f","_type":"reference"},"categoryCode":"biz-8","categoryName":"sales","mainImage":{"_type":"image","asset":{"_ref":"image-15d50f50dbaaaddbf7f2a21f7782d3e97c153259-3901x2195-jpg","_type":"reference"}},"mainImageAltText":"Boost Sales with AI Assistance","parentCategory":{"_ref":"6f0cc24a-55e6-47a4-8f49-269200573b6b","_type":"reference"},"positionLockIn":[{"_key":"49d904b7f57d","_ref":"7dd6b75f-b257-4f78-8a26-1fc822a433c2","_type":"reference"},{"_key":"9a434da3c157","_ref":"50df6c9a-80b4-4182-83b8-7110946475ac","_type":"reference"},{"_key":"8b5c3707b2af","_ref":"fad4383f-1e7b-4f8b-be50-1a7c41529d00","_type":"reference"}],"relatedCategories":[{"_key":"mb89hfp3S5P9KPWcRUAmmT","_ref":"UnZ2THkIAtRzfNq86WfuL0","_type":"reference"}],"seoImage":{"_type":"image","asset":{"_ref":"image-15d50f50dbaaaddbf7f2a21f7782d3e97c153259-3901x2195-jpg","_type":"reference"}},"seoTitle":"AI Sales Tools & Software of [year]","slug":{"_type":"slug","current":"sales-assistant"},"sponsoredTools":[{"_key":"ce24a83b3e36","_ref":"4a17873c-1521-4965-abca-f1f475df46e8","_type":"reference"},{"_key":"921f4b743f36","_ref":"b9a4efa0-4e9c-4689-83d6-69ee8d9314ed","_type":"reference"}],"tableOfContents":{"_type":"tableOfContents","items":[{"_key":"94648a4206e5","anchor":"#ai-sales-tools","label":"AI Sales Tools"},{"_key":"f49713945e34","anchor":"#ethical-considerations-in-ai-sales-practices","label":"Ethical Considerations in AI Sales Practices"},{"_key":"cd72633dcf6c","anchor":"#revolutionizing-sales-training-with-ai","label":"Revolutionizing Sales Training with AI"},{"_key":"97d36a21a961","anchor":"#the-future-of-sales-in-the-ai-era","label":"The Future of Sales in the AI Era"}]},"tagline":"Skyrocket Sales with These [count] AI Tools","title":"AI Sales Tools: Empowering Sales Teams with Precision and Insight"},{"_createdAt":"2023-10-09T18:59:35Z","_id":"e9eaed2c-bcdc-4ac4-a519-5490c8e31117","_rev":"uorVjtmjRg9cfQyWdb18dn","_type":"toolCategory","_updatedAt":"2024-07-02T01:37:35Z","businessFunctionCategory":{"_ref":"92d3a9d0-023a-47b9-b863-9b7e9055f5e0","_type":"reference"},"categoryCode":"chatbot-1","categoryName":"ai chatbots","mainImage":{"_type":"image","asset":{"_ref":"image-24524b531e3afdf9efd43650c6a634ce66596ab4-3901x2195-jpg","_type":"reference"}},"mainImageAltText":"Try These AI Chatbots","parentCategory":{"_ref":"iexqLQ1Ay2ySzDYapFDJwW","_type":"reference"},"positionLockIn":[{"_key":"ceec900053d9","_ref":"e58eeb8b-739d-492c-aa67-80e934e7d732","_type":"reference"},{"_key":"f648bba85f96","_ref":"377ca812-57fd-43a7-82a4-6c2becb28552","_type":"reference"},{"_key":"8b73cf5a506a","_ref":"d1081d5c-f6e7-4b38-b67c-bbca1f1b5d87","_type":"reference"}],"relatedCategories":[{"_key":"fb8833414081","_ref":"UnZ2THkIAtRzfNq86WfuL0","_type":"reference"},{"_key":"7f718f1f8a59","_ref":"UnZ2THkIAtRzfNq86WfjaE","_type":"reference"}],"seoImage":{"_type":"image","asset":{"_ref":"image-24524b531e3afdf9efd43650c6a634ce66596ab4-3901x2195-jpg","_type":"reference"}},"seoTitle":"AI Powered Chatbots of [year]","slug":{"_type":"slug","current":"chatbots"},"sponsoredTools":[{"_key":"e8265fec11fb","_ref":"0ff4e515-1eba-49ad-ae02-06b208924732","_type":"reference"},{"_key":"81203cec132e","_ref":"4a17873c-1521-4965-abca-f1f475df46e8","_type":"reference"}],"tableOfContents":{"_type":"tableOfContents","items":[{"_key":"e5b47341ac03","anchor":"#ai-chatbot-tools","label":"AI Chatbot Tools"},{"_key":"918340d5c1c7","anchor":"#enhancing-engagement-across-industries","label":"Enhancing Engagement Across Industries"},{"_key":"d8ca4322ddfa","anchor":"#the-technical-core-of-ai-chatbots","label":"The Technical Core of AI Chatbots"},{"_key":"35ae32220f76","anchor":"#embracing-the-future-with-ai-chatbots","label":"Embracing the Future with AI Chatbots"}]},"tagline":"Revolutionize Your Communication with These [count] AI Chatbot Tools","title":"AI Chatbot Tools: Elevating Conversations with Intelligent Interactions"}],"toolLabel":"editorsPick","toolName":"Metaforms","toolShortDescription":"AI Forms for Feedback, Surveys and User Research","toolType":["webApp"],"verified":true,"verifiedReason":"Recommended","websiteUrl":"https://metaforms.ai/?utm_source=Futurepedia&utm_medium=4campaigns&utm_campaign=Futurepedia&utm_id=2","youtubeUrl":"https://www.youtube.com/embed/qxJDiBuVMQo?si=iNtzQlAl-zduJc3b"},{"_createdAt":"2023-05-05T00:09:41Z","_id":"f0cffd54-db52-4406-a3d7-fd7ebac94b51","_rev":"zHOqL6olZN7t3wJdfuhl2N","_type":"tool","_updatedAt":"2024-07-25T14:21:12Z","affiliateLink":false,"affiliatePosition":-3031,"defunct":{"defunctReason":"No Longer Available","defunctStatus":false},"duplicate":false,"favCount":79,"id":"f0cffd54-db52-4406-a3d7-fd7ebac94b51","mainImage":{"_type":"image","asset":{"_ref":"image-ed2d2a6bdf7af2eb9d43febe050c0c85ce58fa7f-2517x1233-png","_type":"reference"}},"newFeatures":["API"],"popularityScore":99,"pricing":["Freemium"],"publishedAt":"2024-07-19T00:10:00.000Z","publishedAt_timestamp":1721347800000,"reviewStats":{"reviewCount":1,"reviewScore":5},"slug":{"_type":"slug","current":"pineapple-builder"},"slugIndex":"pineapple-builder","socialLinks":["https://www.facebook.com/Pineapplebuilder/","https://www.linkedin.com/company/pineapplebuilder/","https://twitter.com/Pineapplebuild1","https://www.youtube.com/channel/UCfPVRxnHCNWpMwvLvunwl0Q"],"sponsored":true,"startingPrice":"12/mo","status":"In Review","tagsIndex":["website-builders","e-commerce","seo"],"thumbnail":{"_type":"image","asset":{"_ref":"image-4f1144820f87c59d72ae68e61b8434c49d58cc2b-128x128-png","_type":"reference"}},"thumbnailUrl":"https://www.google.com/s2/favicons?domain=https://www.pineapplebuilder.com/&sz=128","toolCategories":[{"_createdAt":"2023-10-09T18:55:42Z","_id":"0e4e1d6e-b1dd-45e0-b988-85e1633ff4fe","_rev":"cBosSFVB9HVjGjdAduf59z","_type":"toolCategory","_updatedAt":"2024-07-22T08:50:40Z","businessFunctionCategory":{"_ref":"35ddf9f5-ccc9-4ae6-bdc7-c95796824269","_type":"reference"},"categoryCode":"web-2","categoryName":"website builders","mainImage":{"_type":"image","asset":{"_ref":"image-83b76a9fed1e6c70e44d44a5346595b6717078d2-3901x2195-jpg","_type":"reference"}},"mainImageAltText":"Using an AI Website Builder","parentCategory":{"_ref":"6f0cc24a-55e6-47a4-8f49-269200573b6b","_type":"reference"},"positionLockIn":[{"_key":"5cc9010819f9","_ref":"d8d4fb88-8533-4ffe-85e6-435019920e40","_type":"reference"},{"_key":"cd6267eab051","_ref":"01d2f174-41b0-4e9b-9aa4-37325dd7a220","_type":"reference"},{"_key":"7fdd824aa725","_ref":"7a759b10-dc5f-4858-bb8e-c9a39450c9bd","_type":"reference"}],"relatedCategories":[{"_key":"1f59cff77b00","_ref":"18c28701-ecbf-446d-a50d-29285561c411","_type":"reference"},{"_key":"b820584da30b","_ref":"UnZ2THkIAtRzfNq86WfjaE","_type":"reference"},{"_key":"90b81ec40b93","_ref":"kxHCIyVPfR3nkfRNFsIQzs","_type":"reference"}],"seoImage":{"_type":"image","asset":{"_ref":"image-83b76a9fed1e6c70e44d44a5346595b6717078d2-3901x2195-jpg","_type":"reference"}},"seoTitle":"List of AI Website Builders Available in [year]","slug":{"_type":"slug","current":"website-builders"},"sponsoredTools":[{"_key":"b327e7933066","_ref":"f0cffd54-db52-4406-a3d7-fd7ebac94b51","_type":"reference"},{"_key":"2d09a6ab4ef1","_ref":"89c9ac57-99f9-4490-bec5-8edb23857fe7","_type":"reference"}],"tableOfContents":{"_type":"tableOfContents","items":[{"_key":"1b62931c8ebd","anchor":"#ai-website-builder-tools","label":"AI Website Builder Tools"},{"_key":"e274393d7db6","anchor":"#ai-for-seamless-web-creation","label":"AI for Seamless Website Creation"},{"_key":"367da1a847f0","anchor":"#professionals-benefiting-from-ai-website-builders","label":"Professionals Turning to AI Website Builders"}]},"tagline":"[count] AI Website Builder Tools to Design or Modify a Site in 5 Minutes","title":"AI Website Builders - Your Key to Innovation"},{"_createdAt":"2023-02-14T00:16:53Z","_id":"7d1502a2-f805-49f7-8544-4cc2c0c83ed1","_rev":"cBosSFVB9HVjGjdAduf3Yd","_type":"toolCategory","_updatedAt":"2024-07-22T08:40:45Z","businessFunctionCategory":{"_ref":"35ddf9f5-ccc9-4ae6-bdc7-c95796824269","_type":"reference"},"categoryCode":"biz-12","categoryName":"e-commerce","mainImage":{"_type":"image","asset":{"_ref":"image-4fe39f1e7454a0362318836a0c275b051ce0c2d1-3901x2195-jpg","_type":"reference"}},"mainImageAltText":"AI Tools for E-commerce","parentCategory":{"_ref":"6f0cc24a-55e6-47a4-8f49-269200573b6b","_type":"reference"},"positionLockIn":[{"_key":"f97e141cad47","_ref":"fea2c329-5e78-47a7-a17a-6e5145559c8f","_type":"reference"},{"_key":"914f7f39cfea","_ref":"6b24ca4c-5fb1-4f5d-9588-457e2687de98","_type":"reference"},{"_key":"e4f16dfb15f3","_ref":"d813c824-8eb4-41c9-8b31-b76d9d8bc251","_type":"reference"}],"relatedCategories":[{"_key":"8acf0986e7e6","_ref":"UnZ2THkIAtRzfNq86WfzKU","_type":"reference"},{"_key":"6ba93cf76896","_ref":"kxHCIyVPfR3nkfRNFsIAzw","_type":"reference"}],"seoImage":{"_type":"image","asset":{"_ref":"image-4fe39f1e7454a0362318836a0c275b051ce0c2d1-3901x2195-jpg","_type":"reference"}},"seoTitle":"List of E-commerce Tools & Software Using AI in [year]","slug":{"_type":"slug","current":"e-commerce"},"sponsoredTools":[{"_key":"298f1197cde4","_ref":"76fc6bc5-6d6d-4984-bf57-3b3aa40b6c5d","_type":"reference"},{"_key":"597a32c475b9","_ref":"b571f322-256c-4c20-8ec9-18a6e0b652f0","_type":"reference"}],"tableOfContents":{"_type":"tableOfContents","items":[{"_key":"ed48177ce767","anchor":"#ai-e-commerce-tools","label":"AI E-commerce Tools"},{"_key":"14a69db4778b","anchor":"#ais-role-in-revolutionizing-e-commerce","label":"AI's Role in Revolutionizing E-commerce"},{"_key":"4e19ef9dd683","anchor":"#exploring-ais-technological-backbone-in-e-commerce","label":"Exploring AI's Technological Backbone in E-commerce"},{"_key":"7445ed92ad1c","anchor":"#envisioning-ais-future-in-e-commerce","label":"Envisioning AI's Future in E-commerce"}]},"tagline":"Boost Your Online Store with these [count] AI E-Commerce Tools","title":"AI E-Commerce Tools: Elevating Retail Expertise"},{"_createdAt":"2023-01-01T18:45:15Z","_id":"B8o7xf7Q4mKeMEiyAO1uto","_rev":"PhN6UWUpJ3FkntvMO5BeZX","_type":"toolCategory","_updatedAt":"2024-07-21T23:58:25Z","businessFunctionCategory":{"_ref":"e9e5001e-0256-4761-b0f9-6196e003e40f","_type":"reference"},"categoryCode":"text-2","categoryName":"SEO","mainImage":{"_type":"image","asset":{"_ref":"image-c7c2eeced46b107b137d812ca8e8a2aae109e86f-1828x1028-jpg","_type":"reference"}},"mainImageAltText":"AI Tools for SEO","parentCategory":{"_ref":"6f0cc24a-55e6-47a4-8f49-269200573b6b","_type":"reference"},"positionLockIn":[{"_key":"ca0885df1541","_ref":"a464db7c-7db0-45b9-b3ba-d8920c76a767","_type":"reference"},{"_key":"45600ac0da1b","_ref":"5ae2a5fd-8342-4103-b8c6-4fd0ef3da48d","_type":"reference"},{"_key":"9b38b200827a","_ref":"fd2e0efd-7af0-46de-a247-71899a1df043","_type":"reference"}],"relatedCategories":[{"_key":"akCbHjdU4kkPh6hw4qAS28","_ref":"kxHCIyVPfR3nkfRNFsIAzw","_type":"reference"},{"_key":"gXdBF89bngerSBVS973W7x","_ref":"kxHCIyVPfR3nkfRNFsIGZ6","_type":"reference"},{"_key":"2AxzGHi9UL8SWzBp3tGN9s","_ref":"49222099-e48a-4a41-8a5c-1dfcd8f1639f","_type":"reference"}],"seoImage":{"_type":"image","asset":{"_ref":"image-c7c2eeced46b107b137d812ca8e8a2aae109e86f-1828x1028-jpg","_type":"reference"}},"seoTitle":"AI SEO Tools & Software of [year]","slug":{"_type":"slug","current":"seo"},"sponsoredTools":[{"_key":"2b60adf6496b","_ref":"8ef4de39-a3ac-4209-86a6-f653a9bf4bd5","_type":"reference"},{"_key":"cec901d92e87","_ref":"c949fa76-f167-45ba-bdce-ea7ac07d5a10","_type":"reference"}],"tableOfContents":{"_type":"tableOfContents","items":[{"_key":"613f5208aa6e","anchor":"#ai-seo-tools","label":"AI SEO Tools"},{"_key":"d8d7a9ea258f","anchor":"#unveiling-ais-power-in-seo-mastery","label":"Unveiling AI's Power in SEO Mastery"},{"_key":"81aaf5bedf91","anchor":"#leveraging-ai-for-seo-content-strategy-and-development","label":"Leveraging AI for SEO Content Strategy & Development"},{"_key":"25df9e44a6e1","anchor":"#embracing-the-future-with-ai-seo-tools","label":"Embracing the Future with AI SEO Tools"}]},"tagline":"[count] AI SEO Tools to Boost Rankings & Site Traffic","title":"AI SEO Tools - Enhancing Search Rankings with Precision"}],"toolName":"Pineapple Builder","toolShortDescription":"AI-driven, multilingual website creation in seconds.","verified":true,"verifiedReason":"Recommended","websiteUrl":"https://www.pineapplebuilder.com/?utm_source=futurepedia&utm_medium=marketplace&utm_campaign=futurepedia","youtubeUrl":"https://www.youtube.com/embed/UhYJm__Q_TY?si=DyluBT_S_gIZZhUR"},{"_createdAt":"2024-04-15T11:26:15Z","_id":"2032a341-d23d-4c28-b00b-b6efa679baeb","_rev":"GtUuQBYd2CYFh1TUGBoRVz","_type":"tool","_updatedAt":"2024-07-25T04:36:43Z","affiliateLink":false,"affiliatePosition":-3029,"defunct":{"defunctReason":"No Longer Available","defunctStatus":false},"duplicate":false,"favCount":30,"id":"2032a341-d23d-4c28-b00b-b6efa679baeb","mainImage":{"_type":"image","asset":{"_ref":"image-f08d5930a9a6ffcf3779ea6b939563773a5ecb2f-2516x1231-png","_type":"reference"}},"popularityScore":30,"pricing":["Free"],"publishedAt":"2024-04-14T11:26:00.000Z","publishedAt_timestamp":1713093960000,"reviewStats":{"reviewCount":0,"reviewScore":0},"slug":{"_type":"slug","current":"thunderbit"},"slugIndex":"thunderbit","socialLinks":["https://twitter.com/ThunderbitHQ","https://www.linkedin.com/company/thunderbit/about/","https://www.youtube.com/@thunderbit-ai"],"sponsored":true,"status":"In Review","tagsIndex":["no-code","summarizer","email-assistant"],"thumbnail":{"_type":"image","asset":{"_ref":"image-86893aaf588464381a98e3a6fbe2e8ecdc722ca1-512x512-png","_type":"reference"}},"toolCategories":[{"_createdAt":"2023-01-01T18:45:38Z","_id":"UnZ2THkIAtRzfNq86WfjaE","_rev":"fhB3DyuENXT7EjzmqbSG34","_type":"toolCategory","_updatedAt":"2024-07-22T08:34:44Z","businessFunctionCategory":{"_ref":"35ddf9f5-ccc9-4ae6-bdc7-c95796824269","_type":"reference"},"categoryCode":"code-2","categoryName":"low-code/no-code","mainImage":{"_type":"image","asset":{"_ref":"image-eccf568233e6fce14a2ef51836374f04f0cbe95b-3901x2195-jpg","_type":"reference"}},"mainImageAltText":"Low-Code/No-Code AI Tools","parentCategory":{"_ref":"t35bXhDDCHxfvMED4sPmjd","_type":"reference"},"positionLockIn":[{"_key":"775241c2bad8","_ref":"a109cf16-098a-4f18-b8f2-e9d4a2ab6536","_type":"reference"},{"_key":"532bb3eabb6a","_ref":"3d03d5dc-c6df-4a7d-acf6-e23515d0a3e6","_type":"reference"},{"_key":"150c5bcb5426","_ref":"27118f98-3905-4dc9-a684-f14610088274","_type":"reference"}],"relatedCategories":[],"seoImage":{"_type":"image","asset":{"_ref":"image-eccf568233e6fce14a2ef51836374f04f0cbe95b-3901x2195-jpg","_type":"reference"}},"seoTitle":"AI Low Code No Code Tools & Software in [year]","slug":{"_type":"slug","current":"no-code"},"sponsoredTools":[{"_key":"9763d9c57fa3","_ref":"3c4b30bf-d615-4cb1-9d66-ac0f89f89d72","_type":"reference"},{"_key":"351cb5bdc7ab","_ref":"b788f1bf-6599-4d8a-b4c3-0487bfeee3d5","_type":"reference"}],"tableOfContents":{"_type":"tableOfContents","items":[{"_key":"df6dd7a01403","anchor":"#ai-low-code-no-code-tools","label":"AI Low-Code/No-Code Tools"},{"_key":"0556fdb5b8b3","anchor":"#broadening-ais-reach-across-industries","label":"Broadening AI's Reach Across Industries"},{"_key":"3766686be1a5","anchor":"#facilitating-ai-integration-in-varied-professional-fields","label":"Facilitating AI Integration in Varied Professional Fields"},{"_key":"8494dc301a7e","anchor":"#transformative-applications-and-impact","label":"Transformative Applications and Impact "},{"_key":"b6e0e260ba80","anchor":"#the-evolution-and-future-of-no-code-ai","label":"The Evolution and Future of No-Code AI"}]},"tagline":"No Technical Coding Skills? Try These [count] AI Low-Code/No-Code Tools","title":"AI Low-Code/No-Code Tools: Empowering Your Development Journey"},{"_createdAt":"2023-01-01T18:45:18Z","_id":"kxHCIyVPfR3nkfRNFsICDk","_rev":"GmsMATw7FFr29OeLDADDUB","_type":"toolCategory","_updatedAt":"2024-07-22T08:27:26Z","businessFunctionCategory":{"_ref":"ccb51c30-7368-4674-ba43-7672cc76d9ac","_type":"reference"},"categoryCode":"text-4","categoryName":"summarizer","mainImage":{"_type":"image","asset":{"_ref":"image-4aae2fabbd754e614e6778e9785ec65ab9e78a1d-3901x2195-jpg","_type":"reference"}},"mainImageAltText":"Summarize Anything Fast With AI","parentCategory":{"_ref":"52vmteKZvCHTmApSD6vEAb","_type":"reference"},"positionLockIn":[{"_key":"2a1a7bced85c","_ref":"61a17df6-d32f-42f0-b15a-7e3f00588c4f","_type":"reference"},{"_key":"d2d3c00938dd","_ref":"13fcb54c-d551-4325-a093-c3b2fd7c8904","_type":"reference"},{"_key":"325e061004f3","_ref":"18a23c1e-9636-45f0-98b9-e5d9752b3cba","_type":"reference"}],"relatedCategories":[{"_key":"pg35kPkDuc3z4hNPjRhuFY","_ref":"3d3b8adf-2e0e-43eb-b41a-1e246aef944c","_type":"reference"},{"_key":"8rFWsRS1YFTfMysLg3cBVA","_ref":"B8o7xf7Q4mKeMEiyAO3myQ","_type":"reference"},{"_key":"b5868e015d20","_ref":"602689cd-8dd6-4ba4-bb92-d18479a39f69","_type":"reference"}],"seoImage":{"_type":"image","asset":{"_ref":"image-4aae2fabbd754e614e6778e9785ec65ab9e78a1d-3901x2195-jpg","_type":"reference"}},"seoTitle":"AI Summarizer Tools & Software in [year]","slug":{"_type":"slug","current":"summarizer"},"sponsoredTools":[{"_key":"df8d4d474310","_ref":"d6bb94c1-7f42-435f-bfec-e823adeb731f","_type":"reference"},{"_key":"2837e0c08d9e","_ref":"e463c1d9-5e64-47af-b2e2-9309a3c0f383","_type":"reference"}],"tableOfContents":{"_type":"tableOfContents","items":[{"_key":"919ad5580805","anchor":"#ai-summarizer-tools","label":"AI Summarizer Tools"},{"_key":"74e1504936a0","anchor":"#streamlining-information-with-ai-summarization","label":"Streamlining Information with AI Summarization"},{"_key":"b1a3213b7534","anchor":"#choosing-your-ai-summarization-tool","label":"Choosing Your AI Summarization Tool"},{"_key":"964331870b59","anchor":"#embracing-concise-content-with-ai","label":"Embracing Concise Content with AI"}]},"tagline":"Quickly Distill Information with These [count] AI Summarizer Tools","title":"AI Summarizer Tools: Condensing Knowledge for You"},{"_createdAt":"2023-01-01T18:45:23Z","_id":"kxHCIyVPfR3nkfRNFsIGZ6","_rev":"uh6hu98zYycdv8rIUvaRXL","_type":"toolCategory","_updatedAt":"2024-07-02T00:07:15Z","businessFunctionCategory":{"_ref":"bf29aee4-0862-4f8c-8ceb-e67b71c93da0","_type":"reference"},"categoryCode":"text-7","categoryName":"email assistant","parentCategory":{"_ref":"1vD6eDtgeKSQKjJSiByJSn","_type":"reference"},"positionLockIn":[{"_key":"200603468325","_ref":"ecd01918-1b7d-4099-a93b-d47b1ff58edc","_type":"reference"},{"_key":"6d2eb3dac45e","_ref":"4434c1cb-0f26-4487-91ec-b3d305a3e488","_type":"reference"},{"_key":"4ac621a19e57","_ref":"e68716a5-c619-4f53-b77c-a26e73a25668","_type":"reference"}],"relatedCategories":[{"_key":"hvQY95CzDyEoJEzGg5fdyv","_ref":"UnZ2THkIAtRzfNq86WfzKU","_type":"reference"},{"_key":"h57dEjuJKHHsA5YvqdUykS","_ref":"kxHCIyVPfR3nkfRNFsIAzw","_type":"reference"},{"_key":"kpzFW2n66VMMSRibbanhtp","_ref":"B8o7xf7Q4mKeMEiyAO1uto","_type":"reference"},{"_key":"a53xEAsRstpCjCtWgQmsA3","_ref":"UnZ2THkIAtRzfNq86WfuL0","_type":"reference"}],"seoImage":{"_type":"image","asset":{"_ref":"image-6f263c575f145907a54efc97853abf3737498728-1024x1024-webp","_type":"reference"}},"seoTitle":"AI Email Assistant Tools & Software in [year]","slug":{"_type":"slug","current":"email-assistant"},"sponsoredTools":[{"_key":"176174cabf4a","_ref":"548c7cf9-4714-4c14-8e38-ae8ff7f7a0ed","_type":"reference"}]}],"toolLabel":"featured","toolName":"Thunderbit","toolShortDescription":"Transform digital interactions and automate tasks with advanced, accessible AI technology.","toolType":["browserExtension"],"verified":true,"verifiedReason":"Recommended","websiteUrl":"https://thunderbit.com/?utm_source=futurepedia&utm_medium=marketplace&utm_campaign=futurepedia"},{"_createdAt":"2024-04-22T12:30:33Z","_id":"d6bb94c1-7f42-435f-bfec-e823adeb731f","_rev":"ncfXwiFXeqzJRjZBAgAspp","_type":"tool","_updatedAt":"2024-07-25T01:53:30Z","affiliateLink":false,"affiliatePosition":-3028,"defunct":{"defunctReason":"No Longer Available","defunctStatus":false},"duplicate":false,"favCount":18,"id":"d6bb94c1-7f42-435f-bfec-e823adeb731f","mainImage":{"_type":"image","asset":{"_ref":"image-7712563d5facd322a8c6eae7d01f1f388815492c-2527x1302-png","_type":"reference"}},"popularityScore":38,"pricing":["Free Trial"],"publishedAt":"2024-04-22T11:57:40.226Z","publishedAt_timestamp":1713787060226,"reviewStats":{"reviewCount":1,"reviewScore":5},"slug":{"_type":"slug","current":"documind"},"slugIndex":"documind","sponsorOfTheDay":false,"sponsored":true,"startingPrice":"29.93","status":"In Review","tagsIndex":["research-assistant","summarizer"],"thumbnail":{"_type":"image","asset":{"_ref":"image-80aaf0fb24a892d5fe455bcb89be95c136cbb970-225x225-png","_type":"reference"}},"toolCategories":[{"_createdAt":"2023-01-01T18:46:12Z","_id":"B8o7xf7Q4mKeMEiyAO3myQ","_rev":"TLttxgH8a5TkDO3GTNiGsx","_type":"toolCategory","_updatedAt":"2024-07-02T00:16:16Z","businessFunctionCategory":{"_ref":"bf29aee4-0862-4f8c-8ceb-e67b71c93da0","_type":"reference"},"categoryCode":"misc-2","categoryName":"research","mainImage":{"_type":"image","asset":{"_ref":"image-386346ea31d986ea9d0b81a8cb1b9a0d7a8513bf-1266x710-jpg","_type":"reference"}},"mainImageAltText":"Kevin testing AI research tools","parentCategory":{"_ref":"1vD6eDtgeKSQKjJSiByJSn","_type":"reference"},"positionLockIn":[{"_key":"d1a0eaa64a6f","_ref":"c7557112-5f7b-4685-a30b-6e7c4bfa1473","_type":"reference"},{"_key":"20e6ac23d4c8","_ref":"887f666c-b3af-4c7f-b16e-7e656eb3b4a6","_type":"reference"},{"_key":"c3f8139de27a","_ref":"a5e3b0a3-8e44-4d9c-b243-a04f02e12b2b","_type":"reference"}],"relatedCategories":[{"_key":"1aa139c23906","_ref":"51dceb59-b72a-4dfe-a800-dce57c5c024b","_type":"reference"},{"_key":"dcFios7G8cgH6F3hvHR2us","_ref":"kxHCIyVPfR3nkfRNFsIq36","_type":"reference"}],"seoImage":{"_type":"image","asset":{"_ref":"image-386346ea31d986ea9d0b81a8cb1b9a0d7a8513bf-1266x710-jpg","_type":"reference"}},"seoTitle":"Research Tools & Software Using AI in [year]","slug":{"_type":"slug","current":"research-assistant"},"sponsoredTools":[{"_key":"e0496de3b20d","_ref":"94df7685-6bdc-432a-abc3-3207c12b4f39","_type":"reference"},{"_key":"5002596aa3ee","_ref":"4a17873c-1521-4965-abca-f1f475df46e8","_type":"reference"}],"tableOfContents":{"_type":"tableOfContents","items":[{"_key":"2eab8dd0f5ae","anchor":"#ai-research-tools","label":"AI Research Tools"},{"_key":"dacf332f468c","anchor":"#fueling-innovation-across-every-field","label":"Fueling Innovation Across Every Field"},{"_key":"7f993f23cb67","anchor":"#worldwide-collaboration-and-ingenuity","label":"Worldwide Collaboration and Ingenuity"}]},"tagline":"Rapidly Build & Analyze Data Using These [count] AI Research Tools","title":"AI Research Tools - Your Intelligent Partner in Discovery"},{"_createdAt":"2023-01-01T18:45:18Z","_id":"kxHCIyVPfR3nkfRNFsICDk","_rev":"GmsMATw7FFr29OeLDADDUB","_type":"toolCategory","_updatedAt":"2024-07-22T08:27:26Z","businessFunctionCategory":{"_ref":"ccb51c30-7368-4674-ba43-7672cc76d9ac","_type":"reference"},"categoryCode":"text-4","categoryName":"summarizer","mainImage":{"_type":"image","asset":{"_ref":"image-4aae2fabbd754e614e6778e9785ec65ab9e78a1d-3901x2195-jpg","_type":"reference"}},"mainImageAltText":"Summarize Anything Fast With AI","parentCategory":{"_ref":"52vmteKZvCHTmApSD6vEAb","_type":"reference"},"positionLockIn":[{"_key":"2a1a7bced85c","_ref":"61a17df6-d32f-42f0-b15a-7e3f00588c4f","_type":"reference"},{"_key":"d2d3c00938dd","_ref":"13fcb54c-d551-4325-a093-c3b2fd7c8904","_type":"reference"},{"_key":"325e061004f3","_ref":"18a23c1e-9636-45f0-98b9-e5d9752b3cba","_type":"reference"}],"relatedCategories":[{"_key":"pg35kPkDuc3z4hNPjRhuFY","_ref":"3d3b8adf-2e0e-43eb-b41a-1e246aef944c","_type":"reference"},{"_key":"8rFWsRS1YFTfMysLg3cBVA","_ref":"B8o7xf7Q4mKeMEiyAO3myQ","_type":"reference"},{"_key":"b5868e015d20","_ref":"602689cd-8dd6-4ba4-bb92-d18479a39f69","_type":"reference"}],"seoImage":{"_type":"image","asset":{"_ref":"image-4aae2fabbd754e614e6778e9785ec65ab9e78a1d-3901x2195-jpg","_type":"reference"}},"seoTitle":"AI Summarizer Tools & Software in [year]","slug":{"_type":"slug","current":"summarizer"},"sponsoredTools":[{"_key":"df8d4d474310","_ref":"d6bb94c1-7f42-435f-bfec-e823adeb731f","_type":"reference"},{"_key":"2837e0c08d9e","_ref":"e463c1d9-5e64-47af-b2e2-9309a3c0f383","_type":"reference"}],"tableOfContents":{"_type":"tableOfContents","items":[{"_key":"919ad5580805","anchor":"#ai-summarizer-tools","label":"AI Summarizer Tools"},{"_key":"74e1504936a0","anchor":"#streamlining-information-with-ai-summarization","label":"Streamlining Information with AI Summarization"},{"_key":"b1a3213b7534","anchor":"#choosing-your-ai-summarization-tool","label":"Choosing Your AI Summarization Tool"},{"_key":"964331870b59","anchor":"#embracing-concise-content-with-ai","label":"Embracing Concise Content with AI"}]},"tagline":"Quickly Distill Information with These [count] AI Summarizer Tools","title":"AI Summarizer Tools: Condensing Knowledge for You"}],"toolLabel":"none","toolName":"Documind","toolShortDescription":"Revolutionize document handling with AI: analyze, summarize, organize, and collaborate effortlessly.","verified":true,"verifiedReason":"Recommended","websiteUrl":"https://www.documind.chat/?utm_source=futurepedia&amp;utm_medium=marketplace&amp;utm_campaign=futurepedia"},{"_createdAt":"2024-07-11T19:20:13Z","_id":"f29a5818-6086-4f25-9396-1ada44569a90","_rev":"KxWCcpzYx23SnLNWbPxpZw","_type":"tool","_updatedAt":"2024-07-25T04:17:25Z","affiliateLink":false,"affiliatePosition":-3026,"dealText":"20% OFF: FUTUREPEDIA20","defunct":{"defunctReason":"No Longer Available","defunctStatus":false},"duplicate":false,"favCount":18,"id":"f29a5818-6086-4f25-9396-1ada44569a90","mainImage":{"_type":"image","asset":{"_ref":"image-a65f761adb83a5fdd2815905368217458dc2757d-1920x1080-png","_type":"reference"}},"popularityScore":118,"pricing":["Free Trial","Deals"],"publishedAt":"2024-07-12T19:20:00.000Z","publishedAt_timestamp":1720812000000,"reviewStats":{"reviewCount":5,"reviewScore":25},"slug":{"_type":"slug","current":"captain"},"slugIndex":"captain","socialLinks":["https://www.youtube.com/@Content-Captain/videos","https://www.linkedin.com/company/aicontentcaptain/"],"sponsored":true,"startingPrice":"99/mo","status":"In Review","tagsIndex":["marketing","social-media","sales-assistant"],"thumbnail":{"_type":"image","asset":{"_ref":"image-73ba347612db502f7539825432621baf1e36666a-128x128-png","_type":"reference"}},"thumbnailUrl":"https://www.google.com/s2/favicons?domain=https://contentcaptain.io/&sz=128","toolCategories":[{"_createdAt":"2023-10-09T18:57:16Z","_id":"33dbeadd-85a8-48ee-97ec-e6c54ba57d22","_rev":"GmsMATw7FFr29OeLDADOph","_type":"toolCategory","_updatedAt":"2024-07-22T08:41:49Z","businessFunctionCategory":{"_ref":"e9e5001e-0256-4761-b0f9-6196e003e40f","_type":"reference"},"categoryCode":"marketing-1","categoryName":"marketing","mainImage":{"_type":"image","asset":{"_ref":"image-c7c2eeced46b107b137d812ca8e8a2aae109e86f-1828x1028-jpg","_type":"reference"}},"mainImageAltText":"Researching AI Marketing Tools","parentCategory":{"_ref":"6f0cc24a-55e6-47a4-8f49-269200573b6b","_type":"reference"},"positionLockIn":[{"_key":"18b3400cd70b","_ref":"15bbf74a-e399-4fd0-ae0e-1aac06186999","_type":"reference"},{"_key":"e13df31d099f","_ref":"ef5082ef-5cb7-474f-a0b6-c23214df2906","_type":"reference"},{"_key":"b7925eb6cd00","_ref":"3aaaf8cc-3ebb-4757-bb98-4907f6f8cb72","_type":"reference"}],"relatedCategories":[{"_key":"4a244b59e89a","_ref":"18c28701-ecbf-446d-a50d-29285561c411","_type":"reference"},{"_key":"8acfb005e917","_ref":"2650f8d3-164b-4c4b-bb51-aa0f91bf8c0d","_type":"reference"}],"seoImage":{"_type":"image","asset":{"_ref":"image-c7c2eeced46b107b137d812ca8e8a2aae109e86f-1828x1028-jpg","_type":"reference"}},"seoTitle":"Use AI for Marketing with These Tools & Software in [year]","slug":{"_type":"slug","current":"marketing"},"sponsoredTools":[{"_key":"adb7dcdf279d","_ref":"f29a5818-6086-4f25-9396-1ada44569a90","_type":"reference"},{"_key":"07009ed366c8","_ref":"0a5fb7c8-6454-47a3-8e11-15dfe74112c2","_type":"reference"}],"tableOfContents":{"_type":"tableOfContents","items":[{"_key":"6c165aac495a","anchor":"#ai-marketing-tools","label":"AI Marketing Tools"},{"_key":"b47487358bbb","anchor":"#transforming-marketing-strategies","label":"Transforming Marketing Strategies"},{"_key":"58fb636e85b3","anchor":"#enhancing-interactions-and-analytics","label":"Enhancing Interactions and Analytics"},{"_key":"03ba9c19b5cd","anchor":"#empowering-marketers-with-ai","label":"Empowering Marketers with AI"},{"_key":"4a0201901ce0","anchor":"#navigating-the-future-with-ai-driven-marketing","label":"Navigating the Future with AI-Driven Marketing"}]},"tagline":"[count] AI Marketing Tools to Grow Your Brand","title":"AI Marketing Tools - Elevate Your Brand Strategy"},{"_createdAt":"2023-10-12T11:39:35Z","_id":"49222099-e48a-4a41-8a5c-1dfcd8f1639f","_rev":"xR4sqImq24YI7PDNPBqhkX","_type":"toolCategory","_updatedAt":"2024-07-02T01:44:41Z","businessFunctionCategory":{"_ref":"e9e5001e-0256-4761-b0f9-6196e003e40f","_type":"reference"},"categoryCode":"text-8","categoryName":"social media","parentCategory":{"_ref":"6f0cc24a-55e6-47a4-8f49-269200573b6b","_type":"reference"},"positionLockIn":[{"_key":"e28fe8654761","_ref":"9811d4ea-d641-427d-bd38-4b89e6c68869","_type":"reference"},{"_key":"3f58b7b4c37b","_ref":"3eac1b1c-12e9-473f-820b-424f8e80fcd4","_type":"reference"},{"_key":"a7e481ef3cd3","_ref":"d506ce56-e97e-4d23-b492-5cdd52dec412","_type":"reference"}],"relatedCategories":[{"_key":"5DqsnpxEz53kpUQs41zL58","_ref":"kxHCIyVPfR3nkfRNFsIAzw","_type":"reference"},{"_key":"dFb7gFyTYaohC7yaJbEBU8","_ref":"B8o7xf7Q4mKeMEiyAO1uto","_type":"reference"},{"_key":"9Wt15qATqX9yUEM3jo8q48","_ref":"kxHCIyVPfR3nkfRNFsIGZ6","_type":"reference"}],"seoImage":{"_type":"image","asset":{"_ref":"image-3da2446ec6d382d135e2a2b7260d99bd4d72f9b8-1024x1024-webp","_type":"reference"}},"seoTitle":"AI Social Media Tools & Software of [year]","slug":{"_type":"slug","current":"social-media"},"sponsoredTools":[{"_key":"094831f2a86a","_ref":"c949fa76-f167-45ba-bdce-ea7ac07d5a10","_type":"reference"},{"_key":"6e9c7aae52e2","_ref":"bb5524f5-069c-455b-90d2-9fc71ac3bc54","_type":"reference"}]},{"_createdAt":"2023-01-01T18:46:07Z","_id":"UnZ2THkIAtRzfNq86WfzKU","_rev":"0k15mPeIL6qxT66ZGpDLEX","_type":"toolCategory","_updatedAt":"2024-07-02T01:31:47Z","businessFunctionCategory":{"_ref":"e9e5001e-0256-4761-b0f9-6196e003e40f","_type":"reference"},"categoryCode":"biz-8","categoryName":"sales","mainImage":{"_type":"image","asset":{"_ref":"image-15d50f50dbaaaddbf7f2a21f7782d3e97c153259-3901x2195-jpg","_type":"reference"}},"mainImageAltText":"Boost Sales with AI Assistance","parentCategory":{"_ref":"6f0cc24a-55e6-47a4-8f49-269200573b6b","_type":"reference"},"positionLockIn":[{"_key":"49d904b7f57d","_ref":"7dd6b75f-b257-4f78-8a26-1fc822a433c2","_type":"reference"},{"_key":"9a434da3c157","_ref":"50df6c9a-80b4-4182-83b8-7110946475ac","_type":"reference"},{"_key":"8b5c3707b2af","_ref":"fad4383f-1e7b-4f8b-be50-1a7c41529d00","_type":"reference"}],"relatedCategories":[{"_key":"mb89hfp3S5P9KPWcRUAmmT","_ref":"UnZ2THkIAtRzfNq86WfuL0","_type":"reference"}],"seoImage":{"_type":"image","asset":{"_ref":"image-15d50f50dbaaaddbf7f2a21f7782d3e97c153259-3901x2195-jpg","_type":"reference"}},"seoTitle":"AI Sales Tools & Software of [year]","slug":{"_type":"slug","current":"sales-assistant"},"sponsoredTools":[{"_key":"ce24a83b3e36","_ref":"4a17873c-1521-4965-abca-f1f475df46e8","_type":"reference"},{"_key":"921f4b743f36","_ref":"b9a4efa0-4e9c-4689-83d6-69ee8d9314ed","_type":"reference"}],"tableOfContents":{"_type":"tableOfContents","items":[{"_key":"94648a4206e5","anchor":"#ai-sales-tools","label":"AI Sales Tools"},{"_key":"f49713945e34","anchor":"#ethical-considerations-in-ai-sales-practices","label":"Ethical Considerations in AI Sales Practices"},{"_key":"cd72633dcf6c","anchor":"#revolutionizing-sales-training-with-ai","label":"Revolutionizing Sales Training with AI"},{"_key":"97d36a21a961","anchor":"#the-future-of-sales-in-the-ai-era","label":"The Future of Sales in the AI Era"}]},"tagline":"Skyrocket Sales with These [count] AI Tools","title":"AI Sales Tools: Empowering Sales Teams with Precision and Insight"}],"toolLabel":"editorsPick","toolName":"Captain","toolShortDescription":"Automated content creation, engagement, and real-time lead identification.","toolType":["webApp"],"verified":true,"verifiedReason":"Recommended","websiteUrl":"https://www.contentcaptain.io/?utm_source=futurepedia&utm_medium=marketplace&utm_campaign=futurepedia","youtubeUrl":"https://www.youtube.com/embed/UyJuBxztpEo?si=4CDn5E-yabAGe-UC"},{"_createdAt":"2023-12-16T12:46:16Z","_id":"5b50281d-17a8-4e5e-a1a9-99350e89d4ca","_rev":"ncfXwiFXeqzJRjZBAgFkbl","_type":"tool","_updatedAt":"2024-07-25T14:22:01Z","affiliateLink":false,"affiliatePosition":-3025,"defunct":{"defunctReason":"No Longer Available","defunctStatus":false},"duplicate":false,"favCount":28,"id":"5b50281d-17a8-4e5e-a1a9-99350e89d4ca","mainImage":{"_type":"image","asset":{"_ref":"image-b844c32b9d76d64e49695bf5a26249a3fb0fb976-1640x924-png","_type":"reference"}},"popularityScore":268,"pricing":["Freemium"],"publishedAt":"2024-07-12T00:10:00.000Z","publishedAt_timestamp":1720743000000,"reviewStats":{"reviewCount":12,"reviewScore":58},"slug":{"_type":"slug","current":"myessaywriter-ai"},"slugIndex":"myessaywriter-ai","socialLinks":["https://twitter.com/MyEssayWriterai","https://www.instagram.com/myessaywriter.ai/","https://www.youtube.com/channel/UCJuFU9XUezPP8yXEbegGDKw","https://www.pinterest.com/myessaywriterai/","https://www.linkedin.com/company/myessaywriterai/"],"sponsored":true,"status":"In Review","tagsIndex":["writing-generators","education","students"],"thumbnail":{"_type":"image","asset":{"_ref":"image-71e7bae15b593234cb308d778828169a82e8ea89-32x32-png","_type":"reference"}},"thumbnailUrl":"https://www.google.com/s2/favicons?domain=https://www.myessaywriter.ai/&sz=128","toolCategories":[{"_createdAt":"2023-10-09T17:54:28Z","_id":"3d3b8adf-2e0e-43eb-b41a-1e246aef944c","_rev":"IDgY8hZxG7F5EOghfTK2MH","_type":"toolCategory","_updatedAt":"2024-07-02T00:32:57Z","businessFunctionCategory":{"_ref":"ccb51c30-7368-4674-ba43-7672cc76d9ac","_type":"reference"},"categoryCode":"text-1","categoryName":"writing generators","parentCategory":{"_ref":"52vmteKZvCHTmApSD6vEAb","_type":"reference"},"positionLockIn":[{"_key":"86dacbf30797","_ref":"e58eeb8b-739d-492c-aa67-80e934e7d732","_type":"reference"},{"_key":"030bce3566c9","_ref":"61a17df6-d32f-42f0-b15a-7e3f00588c4f","_type":"reference"},{"_key":"5bd864830b04","_ref":"18a23c1e-9636-45f0-98b9-e5d9752b3cba","_type":"reference"}],"relatedCategories":[{"_key":"440a3176ce09","_ref":"B8o7xf7Q4mKeMEiyAO25kO","_type":"reference"},{"_key":"490edc46943e","_ref":"kxHCIyVPfR3nkfRNFsICDk","_type":"reference"}],"seoImage":{"_type":"image","asset":{"_ref":"image-16ca0677b18d22ff9ceb17ae752d4c6626ac7fe3-1024x1024-webp","_type":"reference"}},"seoTitle":"AI Writing Generators in [year]","slug":{"_type":"slug","current":"writing-generators"},"sponsoredTools":[{"_key":"23443e8e687e","_ref":"663a71a7-eb4b-486a-8e38-8479e0661745","_type":"reference"}]},{"_createdAt":"2023-10-12T11:06:54Z","_id":"51dceb59-b72a-4dfe-a800-dce57c5c024b","_rev":"ZyKI2xkKo7EMNMrzTo37YS","_type":"toolCategory","_updatedAt":"2024-07-21T23:53:12Z","categoryCode":"biz-1","categoryName":"education","mainImage":{"_type":"image","asset":{"_ref":"image-ebf8969e512bbd52520a9c4d3e067a8dd0004151-3901x2195-jpg","_type":"reference"}},"mainImageAltText":"Education AI Tools","parentCategory":{"_ref":"6f0cc24a-55e6-47a4-8f49-269200573b6b","_type":"reference"},"positionLockIn":[{"_key":"bed6a3f8915f","_ref":"5fd1c244-2504-4151-ad91-573e605bf1e7","_type":"reference"},{"_key":"652c56fd4616","_ref":"9b31ed37-7b51-4688-b66d-8037cfbc696d","_type":"reference"},{"_key":"01f98d1a5ef8","_ref":"b31d3fe2-fb63-46f6-9be8-7effe8acc421","_type":"reference"}],"seoImage":{"_type":"image","asset":{"_ref":"image-ebf8969e512bbd52520a9c4d3e067a8dd0004151-3901x2195-jpg","_type":"reference"}},"seoTitle":"AI Education Assistant Tools & Software of [year]","slug":{"_type":"slug","current":"education"},"sponsoredTools":[{"_key":"2bf06cf08771","_ref":"d1d4692e-1bcc-41e8-880c-fa5c7fad4d48","_type":"reference"},{"_key":"a4cf447e1065","_ref":"a79b62af-2af8-4452-98a4-649f9403abc3","_type":"reference"}],"tableOfContents":{"_type":"tableOfContents","items":[{"_key":"8ee54273a42f","anchor":"#ai-education-tools","label":"AI Education Tools"},{"_key":"6d232381c12f","anchor":"#revolutionizing-education-with-ai","label":"Revolutionizing Education with AI"},{"_key":"a227c0972d67","anchor":"#ai-driven-educational-environments","label":"AI-Driven Educational Environments"},{"_key":"5157ddb9182d","anchor":"#future-ready-education","label":"\"Future-Ready\" Education"}]},"tagline":"[count] AI Education Tools to Reshape How We Teach & Learn","title":"AI Education Tools: Empowering Educators with Tailored Solutions"},{"_createdAt":"2023-12-19T21:59:42Z","_id":"5cb57bda-cf19-4cc3-99f8-21e07c99f2a6","_rev":"GmsMATw7FFr29OeLDADCKa","_type":"toolCategory","_updatedAt":"2024-07-22T08:22:37Z","categoryCode":"biz-12","categoryName":"students","mainImage":{"_type":"image","asset":{"_ref":"image-ebf8969e512bbd52520a9c4d3e067a8dd0004151-3901x2195-jpg","_type":"reference"}},"mainImageAltText":"Discover AI Tools for Students","parentCategory":{"_ref":"iexqLQ1Ay2ySzDYapFDJwW","_type":"reference"},"positionLockIn":[{"_key":"7ad576e01351","_ref":"7917c942-d8c4-4066-8648-86dd3c8e9f63","_type":"reference"},{"_key":"4ff8f0ee7671","_ref":"d8328a7f-0900-493a-b32a-17ecced98a7b","_type":"reference"},{"_key":"cd9ed2d8621a","_ref":"1d9bd010-fb72-446d-8506-3857bd58ea7e","_type":"reference"}],"relatedCategories":[{"_key":"00fcbf39de0d","_ref":"51dceb59-b72a-4dfe-a800-dce57c5c024b","_type":"reference"},{"_key":"845d71a7dcdc","_ref":"faef9031-7681-4a78-9041-bc0135ea75df","_type":"reference"}],"seoHideFromLists":false,"seoImage":{"_type":"image","asset":{"_ref":"image-ebf8969e512bbd52520a9c4d3e067a8dd0004151-3901x2195-jpg","_type":"reference"}},"seoNoIndex":false,"seoTitle":"AI Tools & Software for Students in [year]","slug":{"_type":"slug","current":"students"},"sponsoredTools":[{"_key":"2f25f238a5a8","_ref":"90a61988-115b-420a-bcf2-8fa569a7a28d","_type":"reference"},{"_key":"582b340064ac","_ref":"74c1582d-bdc1-4fc5-912b-d1937f0119d2","_type":"reference"}],"tableOfContents":{"_type":"tableOfContents","items":[{"_key":"fd677ece5c6d","anchor":"#ai-tools-for-students","label":"AI Tools for Students"},{"_key":"c4fe3383b4a0","anchor":"#customizing-the-learning-experience-with-ai","label":"Customizing the Learning Experience with AI "},{"_key":"c774ecc8e202","anchor":"#boosting-engagement-through-interactive-ai-tools","label":"Boosting Engagement Through Interactive AI Tools"},{"_key":"612f563492f4","anchor":"#equipping-students-for-an-ai-driven-future","label":"Equipping Students for an AI-Driven Future"},{"_key":"2755f2cd31b5","anchor":"#embracing-ais-transformative-potential-in-education","label":"Embracing AI's Transformative Potential in Education"}]},"tagline":"Thrive in an AI-Enhanced Educational World with these [count] AI Tools for Students","title":"AI Tools for Students: Empowering Educational Success with Innovation"}],"toolName":"MyEssayWriter.ai","toolShortDescription":"Streamlines essay writing with AI, ensuring originality and quality.","verified":true,"verifiedReason":"Recommended","websiteUrl":"https://www.myessaywriter.ai/?utm_source=futurepedia&utm_medium=marketplace&utm_campaign=futurepedia"},{"_createdAt":"2024-02-22T21:36:07Z","_id":"376a0082-f06d-4f66-80e4-25c602f45cf9","_rev":"y866BxWvYjYDTtbQqHcPMC","_type":"tool","_updatedAt":"2024-07-25T02:37:03Z","affiliateLink":false,"affiliatePosition":-3024,"defunct":{"defunctReason":"No Longer Available","defunctStatus":false},"duplicate":false,"favCount":22,"id":"376a0082-f06d-4f66-80e4-25c602f45cf9","mainImage":{"_type":"image","asset":{"_ref":"image-8aeec8d4a8df720a353fa005fc641ac243721217-2000x1050-png","_type":"reference"}},"newFeatures":["Waitlist"],"popularityScore":22,"pricing":["Contact for Pricing"],"publishedAt":"2024-02-22T00:10:00.000Z","publishedAt_timestamp":1708560600000,"reviewStats":{"reviewCount":0,"reviewScore":0},"slug":{"_type":"slug","current":"plumb"},"slugIndex":"plumb","socialLinks":["https://twitter.com/useplumb","https://www.linkedin.com/company/useplumb"],"sponsored":true,"status":"In Review","tagsIndex":["education","no-code","ai-agents"],"thumbnail":{"_type":"image","asset":{"_ref":"image-dafe4815a0e8aaf9ccfe24a59d98bea5a2a42f31-3000x3000-png","_type":"reference"}},"thumbnailUrl":"https://www.google.com/s2/favicons?domain=https://useplumb.com/&sz=128","toolCategories":[{"_createdAt":"2023-10-12T11:06:54Z","_id":"51dceb59-b72a-4dfe-a800-dce57c5c024b","_rev":"ZyKI2xkKo7EMNMrzTo37YS","_type":"toolCategory","_updatedAt":"2024-07-21T23:53:12Z","categoryCode":"biz-1","categoryName":"education","mainImage":{"_type":"image","asset":{"_ref":"image-ebf8969e512bbd52520a9c4d3e067a8dd0004151-3901x2195-jpg","_type":"reference"}},"mainImageAltText":"Education AI Tools","parentCategory":{"_ref":"6f0cc24a-55e6-47a4-8f49-269200573b6b","_type":"reference"},"positionLockIn":[{"_key":"bed6a3f8915f","_ref":"5fd1c244-2504-4151-ad91-573e605bf1e7","_type":"reference"},{"_key":"652c56fd4616","_ref":"9b31ed37-7b51-4688-b66d-8037cfbc696d","_type":"reference"},{"_key":"01f98d1a5ef8","_ref":"b31d3fe2-fb63-46f6-9be8-7effe8acc421","_type":"reference"}],"seoImage":{"_type":"image","asset":{"_ref":"image-ebf8969e512bbd52520a9c4d3e067a8dd0004151-3901x2195-jpg","_type":"reference"}},"seoTitle":"AI Education Assistant Tools & Software of [year]","slug":{"_type":"slug","current":"education"},"sponsoredTools":[{"_key":"2bf06cf08771","_ref":"d1d4692e-1bcc-41e8-880c-fa5c7fad4d48","_type":"reference"},{"_key":"a4cf447e1065","_ref":"a79b62af-2af8-4452-98a4-649f9403abc3","_type":"reference"}],"tableOfContents":{"_type":"tableOfContents","items":[{"_key":"8ee54273a42f","anchor":"#ai-education-tools","label":"AI Education Tools"},{"_key":"6d232381c12f","anchor":"#revolutionizing-education-with-ai","label":"Revolutionizing Education with AI"},{"_key":"a227c0972d67","anchor":"#ai-driven-educational-environments","label":"AI-Driven Educational Environments"},{"_key":"5157ddb9182d","anchor":"#future-ready-education","label":"\"Future-Ready\" Education"}]},"tagline":"[count] AI Education Tools to Reshape How We Teach & Learn","title":"AI Education Tools: Empowering Educators with Tailored Solutions"},{"_createdAt":"2023-01-01T18:45:38Z","_id":"UnZ2THkIAtRzfNq86WfjaE","_rev":"fhB3DyuENXT7EjzmqbSG34","_type":"toolCategory","_updatedAt":"2024-07-22T08:34:44Z","businessFunctionCategory":{"_ref":"35ddf9f5-ccc9-4ae6-bdc7-c95796824269","_type":"reference"},"categoryCode":"code-2","categoryName":"low-code/no-code","mainImage":{"_type":"image","asset":{"_ref":"image-eccf568233e6fce14a2ef51836374f04f0cbe95b-3901x2195-jpg","_type":"reference"}},"mainImageAltText":"Low-Code/No-Code AI Tools","parentCategory":{"_ref":"t35bXhDDCHxfvMED4sPmjd","_type":"reference"},"positionLockIn":[{"_key":"775241c2bad8","_ref":"a109cf16-098a-4f18-b8f2-e9d4a2ab6536","_type":"reference"},{"_key":"532bb3eabb6a","_ref":"3d03d5dc-c6df-4a7d-acf6-e23515d0a3e6","_type":"reference"},{"_key":"150c5bcb5426","_ref":"27118f98-3905-4dc9-a684-f14610088274","_type":"reference"}],"relatedCategories":[],"seoImage":{"_type":"image","asset":{"_ref":"image-eccf568233e6fce14a2ef51836374f04f0cbe95b-3901x2195-jpg","_type":"reference"}},"seoTitle":"AI Low Code No Code Tools & Software in [year]","slug":{"_type":"slug","current":"no-code"},"sponsoredTools":[{"_key":"9763d9c57fa3","_ref":"3c4b30bf-d615-4cb1-9d66-ac0f89f89d72","_type":"reference"},{"_key":"351cb5bdc7ab","_ref":"b788f1bf-6599-4d8a-b4c3-0487bfeee3d5","_type":"reference"}],"tableOfContents":{"_type":"tableOfContents","items":[{"_key":"df6dd7a01403","anchor":"#ai-low-code-no-code-tools","label":"AI Low-Code/No-Code Tools"},{"_key":"0556fdb5b8b3","anchor":"#broadening-ais-reach-across-industries","label":"Broadening AI's Reach Across Industries"},{"_key":"3766686be1a5","anchor":"#facilitating-ai-integration-in-varied-professional-fields","label":"Facilitating AI Integration in Varied Professional Fields"},{"_key":"8494dc301a7e","anchor":"#transformative-applications-and-impact","label":"Transformative Applications and Impact "},{"_key":"b6e0e260ba80","anchor":"#the-evolution-and-future-of-no-code-ai","label":"The Evolution and Future of No-Code AI"}]},"tagline":"No Technical Coding Skills? Try These [count] AI Low-Code/No-Code Tools","title":"AI Low-Code/No-Code Tools: Empowering Your Development Journey"},{"_createdAt":"2024-02-26T20:56:33Z","_id":"cbebb50d-e5b0-47db-bb88-af51f877af37","_rev":"GmsMATw7FFr29OeLDA7RFc","_type":"toolCategory","_updatedAt":"2024-07-21T23:55:22Z","businessFunctionCategory":{"_ref":"7caf5c87-ed15-4f88-8541-b4288050c678","_type":"reference"},"categoryCode":"auto-2","categoryName":"ai agents","mainImage":{"_type":"image","asset":{"_ref":"image-abc302fb93d07f0629712a8fa1916f28ff7aac79-1833x1031-jpg","_type":"reference"}},"mainImageAltText":"Showcasing AI Agent Tools","parentCategory":{"_ref":"98026c7c-e50d-4283-925a-13eac7e1c05c","_type":"reference"},"positionLockIn":[{"_key":"68a4b59dc151","_ref":"a23df7c5-a317-4fd2-a1ae-ce4cc16d0269","_type":"reference"},{"_key":"a09b4a7850d1","_ref":"ce6a2538-7e5c-4825-966b-7453d758c711","_type":"reference"},{"_key":"6d68b350c134","_ref":"dff89621-e5a6-43fd-b48a-0ab821fa4acf","_type":"reference"}],"relatedCategories":[{"_key":"16f40a50f89c","_ref":"2cceb05c-d706-400a-95cb-c17daedb1c06","_type":"reference"}],"seoHideFromLists":false,"seoImage":{"_type":"image","asset":{"_ref":"image-abc302fb93d07f0629712a8fa1916f28ff7aac79-1833x1031-jpg","_type":"reference"}},"seoNoIndex":false,"seoTitle":"AI Agent Automations for [year]","slug":{"_type":"slug","current":"ai-agents"},"sponsoredTools":[{"_key":"66ab75355285","_ref":"5d5ef03a-5c22-4e5d-b18c-9e3c0237e88c","_type":"reference"},{"_key":"10acf056d599","_ref":"33b4ed0d-d38a-43a8-ad75-321815c45eb5","_type":"reference"}],"tableOfContents":{"_type":"tableOfContents","items":[{"_key":"166ebf0ca97e","anchor":"#ai-agent-automation-tools","label":"AI Agent Automation Tools"},{"_key":"42071652bdf2","anchor":"#ai-agents-elevating-business-operations","label":"AI Agents Elevating Business Operations"},{"_key":"4c868eb20747","anchor":"#future-prospects-expanding-ai-agent-functions","label":"Future Prospects: Expanding AI Agent Functions"},{"_key":"586bd7feb026","anchor":"#navigating-ai-agent-implementation-challenges","label":"Navigating AI Agent Implementation Challenges"}]},"tagline":"Supercharge Automation with {{count}} AI Agent Tools","title":"AI Agent Tools - Revolutionizing Automation & Productivity"}],"toolName":"Plumb","toolShortDescription":"Create complex AI pipelines effortlessly in a node-based editor.","verified":true,"verifiedReason":"Recommended","websiteUrl":"https://useplumb.com/?utm_source=futurepedia&utm_medium=marketplace&utm_campaign=futurepedia"},{"_createdAt":"2024-04-01T09:37:30Z","_id":"90ce7073-4ea8-4901-9a57-7a758b3c471f","_rev":"PhN6UWUpJ3FkntvMO53IvF","_type":"tool","_updatedAt":"2024-07-18T14:14:28Z","affiliateLink":false,"affiliatePosition":-3023,"defunct":{"defunctReason":"No Longer Available","defunctStatus":false},"duplicate":false,"favCount":18,"id":"90ce7073-4ea8-4901-9a57-7a758b3c471f","mainImage":{"_type":"image","asset":{"_ref":"image-5d4aae53c6e699c00559761269e7de5d6ccfb89d-3452x2342-png","_type":"reference"}},"newFeatures":["Discord Community"],"popularityScore":18,"pricing":["Paid"],"publishedAt":"2024-03-30T09:37:00.000Z","publishedAt_timestamp":1711791420000,"reviewStats":{"reviewCount":0,"reviewScore":0},"slug":{"_type":"slug","current":"botx"},"slugIndex":"botx","socialLinks":["mailto:info@botx.cloud","https://www.facebook.com/botx.eu","https://www.linkedin.com/company/botx-cloud/","https://twitter.com/IvanSivakX","https://www.youtube.com/@botxcloud","https://discord.gg/GdY8fHU8A3"],"sponsored":true,"startingPrice":"189/mo","status":"In Review","tagsIndex":["workflows","no-code","chatbots"],"thumbnail":{"_type":"image","asset":{"_ref":"image-3a42b9bee3b29566741e6c633e197154806b5b9f-500x500-png","_type":"reference"}},"toolCategories":[{"_createdAt":"2024-02-26T20:55:11Z","_id":"2cceb05c-d706-400a-95cb-c17daedb1c06","_rev":"TLttxgH8a5TkDO3GTNiNT1","_type":"toolCategory","_updatedAt":"2024-07-02T01:00:38Z","businessFunctionCategory":{"_ref":"7caf5c87-ed15-4f88-8541-b4288050c678","_type":"reference"},"categoryCode":"auto-1","categoryName":"workflows","parentCategory":{"_ref":"98026c7c-e50d-4283-925a-13eac7e1c05c","_type":"reference"},"positionLockIn":[{"_key":"36ed358ddb67","_ref":"758fc533-5a59-41f1-8cc0-78ad5b91204a","_type":"reference"},{"_key":"823958a3d7e6","_ref":"aaca2aeb-4a80-4ffa-a16b-ae6804321d7a","_type":"reference"},{"_key":"5d95a80304e6","_ref":"7756d567-5f61-49f5-9eb6-5edf6b507c37","_type":"reference"}],"relatedCategories":[{"_key":"959f67187c0d","_ref":"cbebb50d-e5b0-47db-bb88-af51f877af37","_type":"reference"}],"seoHideFromLists":false,"seoImage":{"_type":"image","asset":{"_ref":"image-67846f650e479495d135d8f527ca9fbed5eee39b-1024x1024-webp","_type":"reference"}},"seoNoIndex":false,"seoTitle":"Workflow Automation Tools of [year]","slug":{"_type":"slug","current":"workflows"},"sponsoredTools":[{"_key":"1af34f3bb650","_ref":"5d5ef03a-5c22-4e5d-b18c-9e3c0237e88c","_type":"reference"}],"tagline":"Optimize Routine Operations with {{count}} AI Workflow Tools"},{"_createdAt":"2023-01-01T18:45:38Z","_id":"UnZ2THkIAtRzfNq86WfjaE","_rev":"j6VM9i3QEkD86kvVW8svuX","_type":"toolCategory","_updatedAt":"2024-07-16T04:42:45Z","businessFunctionCategory":{"_ref":"35ddf9f5-ccc9-4ae6-bdc7-c95796824269","_type":"reference"},"categoryCode":"code-2","categoryName":"low-code/no-code","mainImage":{"_type":"image","asset":{"_ref":"image-eccf568233e6fce14a2ef51836374f04f0cbe95b-3901x2195-jpg","_type":"reference"}},"mainImageAltText":"Low-Code/No-Code AI Tools","parentCategory":{"_ref":"t35bXhDDCHxfvMED4sPmjd","_type":"reference"},"positionLockIn":[{"_key":"775241c2bad8","_ref":"a109cf16-098a-4f18-b8f2-e9d4a2ab6536","_type":"reference"},{"_key":"532bb3eabb6a","_ref":"3d03d5dc-c6df-4a7d-acf6-e23515d0a3e6","_type":"reference"},{"_key":"150c5bcb5426","_ref":"27118f98-3905-4dc9-a684-f14610088274","_type":"reference"}],"relatedCategories":[],"seoImage":{"_type":"image","asset":{"_ref":"image-eccf568233e6fce14a2ef51836374f04f0cbe95b-3901x2195-jpg","_type":"reference"}},"seoTitle":"AI Low Code No Code Tools & Software in [year]","slug":{"_type":"slug","current":"no-code"},"tableOfContents":{"_type":"tableOfContents","items":[{"_key":"df6dd7a01403","anchor":"#ai-low-code-no-code-tools","label":"AI Low-Code/No-Code Tools"},{"_key":"0556fdb5b8b3","anchor":"#broadening-ais-reach-across-industries","label":"Broadening AI's Reach Across Industries"},{"_key":"3766686be1a5","anchor":"#facilitating-ai-integration-in-varied-professional-fields","label":"Facilitating AI Integration in Varied Professional Fields"},{"_key":"8494dc301a7e","anchor":"#transformative-applications-and-impact","label":"Transformative Applications and Impact "},{"_key":"b6e0e260ba80","anchor":"#the-evolution-and-future-of-no-code-ai","label":"The Evolution and Future of No-Code AI"}]},"tagline":"No Technical Coding Skills? Try These [count] AI Low-Code/No-Code Tools","title":"AI Low-Code/No-Code Tools: Empowering Your Development Journey"},{"_createdAt":"2023-10-09T18:59:35Z","_id":"e9eaed2c-bcdc-4ac4-a519-5490c8e31117","_rev":"uorVjtmjRg9cfQyWdb18dn","_type":"toolCategory","_updatedAt":"2024-07-02T01:37:35Z","businessFunctionCategory":{"_ref":"92d3a9d0-023a-47b9-b863-9b7e9055f5e0","_type":"reference"},"categoryCode":"chatbot-1","categoryName":"ai chatbots","mainImage":{"_type":"image","asset":{"_ref":"image-24524b531e3afdf9efd43650c6a634ce66596ab4-3901x2195-jpg","_type":"reference"}},"mainImageAltText":"Try These AI Chatbots","parentCategory":{"_ref":"iexqLQ1Ay2ySzDYapFDJwW","_type":"reference"},"positionLockIn":[{"_key":"ceec900053d9","_ref":"e58eeb8b-739d-492c-aa67-80e934e7d732","_type":"reference"},{"_key":"f648bba85f96","_ref":"377ca812-57fd-43a7-82a4-6c2becb28552","_type":"reference"},{"_key":"8b73cf5a506a","_ref":"d1081d5c-f6e7-4b38-b67c-bbca1f1b5d87","_type":"reference"}],"relatedCategories":[{"_key":"fb8833414081","_ref":"UnZ2THkIAtRzfNq86WfuL0","_type":"reference"},{"_key":"7f718f1f8a59","_ref":"UnZ2THkIAtRzfNq86WfjaE","_type":"reference"}],"seoImage":{"_type":"image","asset":{"_ref":"image-24524b531e3afdf9efd43650c6a634ce66596ab4-3901x2195-jpg","_type":"reference"}},"seoTitle":"AI Powered Chatbots of [year]","slug":{"_type":"slug","current":"chatbots"},"sponsoredTools":[{"_key":"e8265fec11fb","_ref":"0ff4e515-1eba-49ad-ae02-06b208924732","_type":"reference"},{"_key":"81203cec132e","_ref":"4a17873c-1521-4965-abca-f1f475df46e8","_type":"reference"}],"tableOfContents":{"_type":"tableOfContents","items":[{"_key":"e5b47341ac03","anchor":"#ai-chatbot-tools","label":"AI Chatbot Tools"},{"_key":"918340d5c1c7","anchor":"#enhancing-engagement-across-industries","label":"Enhancing Engagement Across Industries"},{"_key":"d8ca4322ddfa","anchor":"#the-technical-core-of-ai-chatbots","label":"The Technical Core of AI Chatbots"},{"_key":"35ae32220f76","anchor":"#embracing-the-future-with-ai-chatbots","label":"Embracing the Future with AI Chatbots"}]},"tagline":"Revolutionize Your Communication with These [count] AI Chatbot Tools","title":"AI Chatbot Tools: Elevating Conversations with Intelligent Interactions"}],"toolName":"BotX","toolShortDescription":"Revolutionize business automation with no-code AI, seamless integrations, and customizable workflows.","toolType":["webApp"],"verified":true,"verifiedReason":"Recommended","websiteUrl":"https://www.botx.cloud/?utm_source=futurepedia&utm_medium=marketplace&utm_campaign=futurepedia","youtubeUrl":"https://www.youtube.com/embed/gUIWWYEXzZk?si=iBjkZ9oFepUzCS1q"}],"count":5733}